Workbook
Name Opt_RACI: '99_选项字典'!$I$2:$I$6
Name Opt_部门名称: '99_选项字典'!$K$2:$K$8
Name Opt_岗位名称: '99_选项字典'!$M$2:$M$27
Name Opt_岗位状态: '99_选项字典'!$G$2:$G$6
Name Opt_关键岗位: '99_选项字典'!$D$2:$D$4
Name Opt_管理确认人: '99_选项字典'!$N$2:$N$10
Name Opt_管理域: '99_选项字典'!$H$2:$H$14
Name Opt_确认状态: '99_选项字典'!$J$2:$J$6
Name Opt_人员状态: '99_选项字典'!$B$2:$B$7
Name Opt_任职性质: '99_选项字典'!$C$2:$C$6
Name Opt_组织层级: '99_选项字典'!$A$2:$A$8
Name Opt_组织单元: '99_选项字典'!$L$2:$L$20
Name Opt_组织类型: '99_选项字典'!$E$2:$E$8
Name Opt_组织状态: '99_选项字典'!$F$2:$F$6

Sheet 00_总览与说明
A1: 鑫犇电子有限公司｜组织架构与职责矩阵模板
A2: 先填主数据，再生成管理结论。不要直接在RACI里凭感觉填部门名称；所有人员、部门、岗位先在主数据表建立唯一编号。
A4: 模板使用顺序
A5: 步骤 | B5: 工作表 | C5: 填写要求
A6: 1 | B6: 01_员工名单 | C6: 一行一个人；员工ID和上级员工ID是组织树的骨架。
A7: 2 | B7: 02_组织单元 | C7: 一行一个公司/部门/班组组织单元；组织单元ID必须唯一。
A8: 3 | B8: 03_岗位字典 | C8: 一行一个岗位；岗位ID用于后续职责、能力和替代人管理。
A9: 4 | B9: 04_RACI职责矩阵 | C9: 一行一项管理活动；每行只能有一个A，至少一个R。
A10: 5 | B10: 05_确认清单 | C10: 将负责人、审批权、兼岗和边界争议登记，不要靠口头记忆。
A13: 质量规则（必须遵守）
A14: • 组织树：根节点只有一个；除根节点外，每个人必须有且只有一个直接上级员工ID。
A15: • RACI：每项活动必须且只能有一个A；没有A的事项不能视为已授权；至少一个R负责执行。
A16: • 职责：A是最终对结果负责和有批准权的人，不是“参与过的人”；R是实际做事的人。
A17: • 状态：当前事实和未来规划分开；不确定信息统一写“待确认”，不得凭经验补全。
A18: • 版本：修改组织关系、岗位或职责矩阵时，填写变更日期、变更原因和确认人。
A21: 自动检查看板
A22: 指标 | B22: 数值 | C22: 解释
A23: 人员总数 | B23: =COUNTIF('01_员工名单'!A5:A101,"<>") | C23: 填写数据后自动统计
A24: 在岗人数 | B24: =COUNTIFS('01_员工名单'!A5:A101,"<>",'01_员工名单'!G5:G101,"在岗") | C24: 填写数据后自动统计
A25: 组织单元数 | B25: =COUNTIF('02_组织单元'!A5:A52,"<>") | C25: 填写数据后自动统计
A26: 岗位数 | B26: =COUNTIF('03_岗位字典'!A5:A83,"<>") | C26: 填写数据后自动统计
A27: RACI事项数 | B27: =COUNTIF('04_RACI职责矩阵'!A5:A86,"<>") | C27: 填写数据后自动统计
A28: RACI待修正事项 | B28: =COUNTIF('04_RACI职责矩阵'!Z5:Z86,"<>OK")-COUNTBLANK('04_RACI职责矩阵'!A5:A86) | C28: 填写数据后自动统计
A30: 本次已填入：惠州市鑫犇电子有限公司原始组织机构图中的2个公司岗位、5个部门、12个下属组织/岗位单元。组织架构骨架已确认；未完成事项仅在“05_确认清单”中跟踪。
A31: 已吸收：组织机构.xlsx、附件3岗位职责文件、职工名册20260808；员工主数据只保留姓名、工种、编号和组织归属，敏感身份与联系方式不复制。

Sheet 01_组织架构图
A1: 鑫犇电子有限公司｜现行组织架构图

Sheet 01_员工名单
A1: 01｜员工名单
A2: 用途：组织治理、职责分配和人员规模确认。完整人事敏感资料仅在人事主数据中管理。
A4: 员工ID | B4: 上级员工ID | C4: 姓名 | D4: 岗位名称 | E4: 兼任岗位 | F4: 员工任职阶段 | G4: 人员状态
A5: EMP-0001 | B5: EMP-0017 | C5: 王小平 | D5: 冲压车间负责人 | F5: 正式员工 | G5: 在岗
A6: EMP-0002 | B6: EMP-0017 | C6: 王立芳 | D6: 制程巡检组长 | F6: 正式员工 | G6: 在岗
A7: EMP-0003 | B7: EMP-0002 | C7: 尹宗琴 | D7: 质检员（制程巡检） | F7: 正式员工 | G7: 在岗
A8: EMP-0004 | B8: EMP-0002 | C8: 伍伟 | D8: 质检员（制程巡检） | F8: 正式员工 | G8: 在岗
A9: EMP-0005 | B9: EMP-0002 | C9: 余永满 | D9: 质检员（制程巡检） | F9: 正式员工 | G9: 在岗
A10: EMP-0006 | B10: EMP-0002 | C10: 雷杰 | D10: 质检员（制程巡检） | F10: 正式员工 | G10: 在岗
A11: EMP-0007 | B11: EMP-0002 | C11: 李伟芳 | D11: 质检员（制程巡检） | F11: 正式员工 | G11: 在岗
A12: EMP-0008 | B12: EMP-0020 | C12: 余永珍 | D12: 炊事员 | F12: 正式员工 | G12: 在岗
A13: EMP-0009 | B13: EMP-0020 | C13: 杨达友 | D13: 门卫 | F13: 正式员工 | G13: 在岗
A14: EMP-0010 | B14: EMP-0020 | C14: 尹昌廷 | D14: 门卫 | F14: 正式员工 | G14: 在岗
A15: EMP-0011 | B15: EMP-0013 | C15: 冯文举 | D15: 仓库员 | F15: 正式员工 | G15: 在岗
A16: EMP-0012 | B16: EMP-0013 | C16: 蔡光怀 | D16: 包装工 | F16: 正式员工 | G16: 在岗
A17: EMP-0013 | B17: EMP-0017 | C17: 王珊兰 | D17: 质检员（来料/出货检验） | E17: 仓储组长;成品出货检验组长 | F17: 正式员工 | G17: 在岗
A18: EMP-0014 | B18: EMP-0013 | C18: 赵荔 | D18: 包装工 | F18: 正式员工 | G18: 在岗
A19: EMP-0015 | B19: EMP-0019 | C19: 王秋红 | D19: 跟单员 | F19: 正式员工 | G19: 在岗
A20: EMP-0016 | B20: EMP-0017 | C20: 尹杰 | D20: 生产计划员 | E20: 采购员;人事员 | F20: 正式员工 | G20: 在岗
A21: EMP-0017 | B21: EMP-0019 | C21: 李天友 | D21: 品质部负责人 | E21: 生产部负责人 | F21: 正式员工 | G21: 在岗
A22: EMP-0018 | B22: EMP-0019 | C22: 刘东 | D22: 模具技术负责人 | F22: 正式员工 | G22: 在岗
A23: EMP-0019 | B23: / | C23: 王晓华 | D23: 总经理 | E23: 营运部负责人;行政部负责人 | F23: 正式员工 | G23: 在岗
A24: EMP-0020 | B24: / | C24: 王勇 | D24: 董事长 | E24: 财务部负责人; 出纳;会计 | F24: 正式员工 | G24: 在岗
A25: EMP-0021 | B25: EMP-0017 | C25: 马金军 | D25: 清洗车间负责人 | F25: 正式员工 | G25: 在岗
A26: EMP-0022 | B26: EMP-0021 | C26: 余永政 | D26: 清洗工 | F26: 正式员工 | G26: 在岗
A27: EMP-0023 | B27: EMP-0021 | C27: 雷国才 | D27: 清洗工 | F27: 正式员工 | G27: 在岗
A28: EMP-0024 | B28: EMP-0021 | C28: 王正光 | D28: 清洗工 | F28: 正式员工 | G28: 在岗
A29: EMP-0025 | B29: EMP-0021 | C29: 王文开 | D29: 清洗工 | F29: 正式员工 | G29: 在岗
A30: EMP-0026 | B30: EMP-0018 | C30: 吴闻根 | D30: 上机壳模具组长 | F30: 正式员工 | G30: 在岗
A31: EMP-0027 | B31: EMP-0026 | C31: 陈英坤 | D31: 模具检修工 | F31: 正式员工 | G31: 在岗
A32: EMP-0028 | B32: EMP-0026 | C32: 屠园园 | D32: 模具检修工 | F32: 正式员工 | G32: 在岗
A33: EMP-0029 | B33: EMP-0026 | C33: 邓宏军 | D33: 模具检修工 | F33: 正式员工 | G33: 在岗
A34: EMP-0030 | B34: EMP-0018 | C34: 王杰 | D34: 下机壳模具组长 | F34: 正式员工 | G34: 在岗
A35: EMP-0031 | B35: EMP-0030 | C35: 陈仕波 | D35: 模具检修工 | F35: 正式员工 | G35: 在岗
A36: EMP-0032 | B36: EMP-0030 | C36: 杨茗杰 | D36: 模具检修工 | F36: 正式员工 | G36: 在岗
... A48: EMP-0044 | B48: EMP-0026 | C48: 陈仕宁 | D48: 模具检修工 | F48: 正式员工 | G48: 在岗

Sheet 02_组织单元
A1: 02｜组织单元主数据
A2: 公司组织架构按“公司—部门—班组”管理；董事长、总经理归入公司层级；包装不作为独立组织单元，相关人员归入仓储组。
A4: 组织单元ID* | B4: 组织单元名称* | C4: 组织层级 | D4: 上级组织单元ID | E4: 负责人员工ID | F4: 负责人姓名（可选） | G4: 组织状态 | H4: 现有人数 | I4: 计划编制 | J4: 核心定位 | K4: 主要输出物 | L4: 备注 | M4: 月度汇报对象 | N4: 月度汇报周期
A5: ORG-ROOT | B5: 惠州市鑫犇电子有限公司 | C5: 公司 | E5: / | F5: / | G5: 现行 | J5: 公司主体 | K5: 1、《年度经营目标》；2、《重大审批记录》；3、《公司级制度文件》；4、《组织架构总文件》；5、《ISO9001质量体系文件》 | L5: 公司为组织管理概念，不配置实体负责人；本字段不填写，以“/”标记。 | M5: 董事长 | N5: 每月5日前
A6: ORG-CHAIR | B6: 董事长 | C6: 公司 | D6: ORG-ROOT | E6: EMP-0020 | F6: 王勇 | G6: 现行 | J6: 公司治理与重大决策 | K6: 1、《战略规划文件》；2、《重大事项审批记录》 | L6: 董事长：王勇（EMP-0020）。 | M6: 公司 | N6: 每月5日前
A7: ORG-GM | B7: 总经理 | C7: 公司 | D7: ORG-ROOT | E7: EMP-0019 | F7: 王晓华 | G7: 现行 | J7: 公司经营管理与跨部门协调 | K7: 1、《经营管理会议纪要》；2、《月度经营分析报告》；3、《重点事项跟踪表》 | L7: 与董事长同属公司层级；负责日常经营管理和五个一级部门统筹协调。 | M7: 董事长 | N7: 每月5日前
A8: ORG-ADM | B8: 行政部 | C8: 部门 | D8: ORG-GM | E8: EMP-0020 | F8: 王晓华 | G8: 现行 | J8: 行政管理部门 | K8: 1、《文件员工档案》；2、《安全管理台账》；3、《安全教育培训台账》；4、《后勤管理记录》；5、《招聘/离职资料》 | M8: 总经理 | N8: 每月3日前
A9: ORG-OPS | B9: 营运部 | C9: 部门 | D9: ORG-GM | E9: EMP-0019 | F9: 王晓华 | G9: 现行 | J9: 运营管理部门 | K9: 1、《订单评审文件》；2、《原材料采购申购单》；3、《仓储盘点汇总》；4、《出货检测报告》 | M9: 总经理 | N9: 每月3日前
A10: ORG-PROD | B10: 生产部 | C10: 部门 | D10: ORG-GM | E10: EMP-0017 | F10: 李天友 | G10: 现行 | J10: 生产管理部门 | K10: 1、《生产任务单》；2、《日产量报表》；3、《设备日点检汇总表》；4、《生产异常记录》 | M10: 总经理 | N10: 每月3日前
A11: ORG-QA | B11: 品质部 | C11: 部门 | D11: ORG-GM | E11: EMP-0017 | F11: 李天友 | G11: 现行 | J11: 品质管理部门 | K11: 1、《IQC来料检验报告》；2、《制程/终检检验记录》；3、《不合格品处置记录》；4、《客诉闭环报告》；5、《量具校准台账》；6、《受控质量文件》 | M11: 总经理 | N11: 每月3日前
A12: ORG-FIN | B12: 财务部 | C12: 部门 | D12: ORG-GM | E12: EMP-0020 | F12: 王勇 | G12: 现行 | J12: 财务管理部门 | K12: 1、《会计凭证》；2、《月度财务报表》；3、《税务申报表》；4、《资金计划》；5、《付款审批记录》；6、《成本分析报告》 | M12: 董事长、总经理 | N12: 每月5日前
A13: ORG-PROD-WORK | B13: 冲压车间 | C13: 班组 | D13: ORG-PROD | E13: EMP-0001 | F13: 王小平 | G13: 现行 | J13: 生产执行单元 | K13: 1、《冲压半成品/成品》；2、《冲床设备点检记录》；3、《工位生产日报》；4、《现场不良隔离记录》 | L13: 按本次组织架构确认更新；月度汇报内容沿用原定义，后续按班组职责细化。 | M13: 生产部负责人 | N13: 每月2日前
A14: ORG-PROD-WASH | B14: 清洗车间 | C14: 班组 | D14: ORG-PROD | E14: EMP-0021 | F14: 马金军 | G14: 现行 | J14: 产品清洗单元 | K14: 1、《清洗作业记录》；2、《清洗设备点检表》；3、《不良隔离记录》 | L14: 清洗车间已纳入现行组织架构，马金军为清洗组长。 | M14: 生产部负责人 | N14: 每月2日前
A15: ORG-OPS-WH | B15: 仓储组 | C15: 班组 | D15: ORG-OPS | E15: EMP-0013 | F15: 王珊兰 | G15: 现行 | J15: 仓储管理单元 | K15: 1、《物料出入库单据》；2、《出入库存台账（包括纸质和电子台账）》；3、《出入库存立牌》；4、《季度盘点表》 | L15: 按本次组织架构确认更新；月度汇报内容沿用原定义，后续按班组职责细化。 | M15: 营运部负责人 | N15: 每月2日前
A16: ORG-OPS-PUR | B16: 采购组 | C16: 班组 | D16: ORG-OPS | E16: EMP-0016 | F16: 尹杰 | G16: 现行 | J16: 采购单元 | K16: 1、《采购订单》；2、《询比价记录》；3、《采购交期跟进台账》；4、《来料异常记录》 | L16: 按本次组织架构确认更新；月度汇报内容沿用原定义，后续按班组职责细化。 | M16: 营运部负责人 | N16: 每月2日前
A17: ORG-OPS-BIZ | B17: 业务组 | C17: 班组 | D17: ORG-OPS | E17: EMP-0015 | F17: 王秋红 | G17: 现行 | J17: 业务单元 | K17: 1、《订单评审记录》；2、《订单台账》；3、《客户沟通记录》；4、《出货通知单》 | L17: 按本次组织架构确认更新；月度汇报内容沿用原定义，后续按班组职责细化。 | M17: 营运部负责人 | N17: 每月2日前
A18: ORG-ADM-LOG | B18: 后勤组 | C18: 班组 | D18: ORG-ADM | E18: EMP-0020 | F18: 王勇 | G18: 现行 | J18: 后勤保障单元 | K18: 1、《访客出入登记本》；2、《厂区巡逻记录》；3、《食堂消毒记录》 | L18: 按本次组织架构确认更新；月度汇报内容沿用原定义，后续按班组职责细化。 | M18: 行政部负责人 | N18: 每月2日前
A19: ORG-ADM-HR | B19: 人事组 | C19: 班组 | D19: ORG-ADM | E19: EMP-0016 | F19: 尹杰 | G19: 现行 | J19: 人事管理单元 | K19: 1、《员工人事档案》；2、《入离职表单》；3、《月度考勤汇总表》；4、《招聘台账》；5、《社保办理记录》 | L19: 按本次组织架构确认更新；月度汇报内容沿用原定义，后续按班组职责细化。 | M19: 行政部负责人 | N19: 每月2日前
A20: ORG-PROD-TECH | B20: 工程技术组 | C20: 班组 | D20: ORG-PROD | E20: EMP-0018 | F20: 刘东 | G20: 现行 | J20: 技术支持单元 | K20: 1、《模具技术评审记录》；2、《产品工艺文件》；3、《技术改善报告》；4、《工艺变更建议文档》 | L20: 按本次组织架构确认更新；月度汇报内容沿用原定义，后续按班组职责细化。 | M20: 总经理 | N20: 每月2日前
A21: ORG-PROD-MOLD | B21: 模具维修组 | C21: 班组 | D21: ORG-PROD | E21: EMP-0026 | F21: 吴闻根 | G21: 现行 | J21: 模具制造/维修单元 | K21: 1、《模具维修保养记录》；2、《模具台账》；3、《修模改模图纸台账》；4、《班组巡检记录》 | L21: 架构层面保留一个“模具维修组”；岗位层面可分上机壳模具组长、下机壳模具组长。 | M21: 模具技术负责人 | N21: 每月2日前
A22: ORG-QA-IPQC | B22: 制程巡检组 | C22: 班组 | D22: ORG-QA | E22: EMP-0017 | F22: 李天友 | G22: 现行 | J22: 制程质量巡检单元 | K22: 1、《制程巡检记录》；2、《制程异常反馈单》 | L22: 制程巡检、首件复核和现场不良隔离。 | M22: 品质部负责人 | N22: 每月2日前
A23: ORG-QA-FG | B23: 成品出货检验组 | C23: 班组 | D23: ORG-QA | E23: EMP-0013 | F23: 王珊兰 | G23: 现行 | J23: 品质管理班组 | K23: 1、《月度制程/成品检验汇总》；2、《出货质量报告》；3、《客户质量异常跟踪》 | L23: 合并承担来料检查、成品检验和出货检验职责；分别按来料、成品和出货检验要求记录与处理异常。 | M23: 品质部负责人 | N23: 每月2日前
A24: ORG-FIN-ACC | B24: 会计组 | C24: 班组 | D24: ORG-FIN | E24: EMP-0020 | F24: 王勇 | G24: 现行 | J24: 财务班组 | K24: 1、《月度财务报表》；2、《税务申报汇总》；3、《成本分析报告》 | L24: 会计核算与税务 | M24: 财务负责人 | N24: 每月2日前
A25: ORG-FIN-CASH | B25: 出纳组 | C25: 班组 | D25: ORG-FIN | E25: EMP-0020 | F25: 王勇 | G25: 现行 | J25: 财务班组 | K25: 1、《月度资金收支汇总》；2、《银行对账》；3、《付款执行清单》 | L25: 资金收付与台账 | M25: 财务负责人 | N25: 每月2日前

Sheet 03_岗位字典
A1: 03｜岗位字典
A2: 岗位名称可根据实际工作需要自定义；岗位所属组织单元及岗位层级须引用“02_组织单元”中的正式架构。岗位层级格式为“公司/部门/班组＋负责人/成员”。
A4: 岗位ID* | B4: 岗位名称* | C4: 所属组织单元ID | D4: 岗位层级 | E4: 岗位状态 | F4: 岗位目的 | G4: 核心职责 | H4: 岗位输出物 | I4: 关键权限 | J4: 任职要求/能力 | K4: 替代岗位ID | L4: 备注
A5: POS-CHAIR | B5: 董事长 | C5: ORG-ROOT | D5: 公司负责人 | E5: 现行 | F5: 把控公司战略方向，重大经营决策、风险管控 | G5: 公司战略规划；重大投资、人事、财务事项审批；监督总经理经营履职；重大对外决策 | H5: 《战略规划文件》、《重大事项审批记录》 | I5: 重大投资审批权、高层人事任免权、重大财务审批权 | J5: 企业经营战略、风险管理、行业研判能力 | K5: POS-GM
A6: POS-GM | B6: 总经理 | C6: ORG-ROOT | D6: 公司负责人 | E6: 现行 | F6: 全面负责公司日常经营管理，对经营结果最终负责 | G6: 执行董事会战略；统筹各部门运营；经营目标拆解落地；跨部门冲突协调；经营绩效管控；重大客户与供应商管理 | H6: 《年度经营计划》、《部门绩效考核》《经营管理会议纪要》、《月度经营分析报告》、《重点事项跟踪表》 | I6: 日常经营决策权、部门工作调度权、一般人事审批权 | J6: 制造业全盘运营管理，生产质量财务综合管理能力 | K6: POS-CHAIR
A7: POS-FIN-MGR | B7: 财务部负责人 | C7: ORG-FIN | D7: 部门负责人 | E7: 现行 | F7: 统筹财务核算、资金、税务、成本管理，保障资金安全合规 | G7: 全盘账务管理；资金计划与付款审批；税务申报；成本核算；财务报表；会计出纳工作监督复核；内控风险把控 | H7: 《资金计划》、《月度财务报表》、《成本分析报告》 | I7: 资金付款复核审批、账务审核、财务制度拟定权 | J7: 财务全盘管理、税务、成本核算、内控风险识别 | K7: POS-CHAIR
A8: POS-OPS-MGR | B8: 营运部负责人 | C8: ORG-OPS | D8: 部门负责人 | E8: 现行 | F8: 合同订单、客户、采购和仓储运营管理 | G8: 合同/订单评审、客户沟通、业务跟单、采购、供应商、物料入库和仓储控制 | H8: 《订单评审文件》、《仓储盘点汇总报告》 | I8: 订单评审决定权、供应商准入建议权 | J8: 订单供应链管理，客户及供应商统筹管理 | K8: POS-GM
A9: POS-ADM-MGR | B9: 行政部负责人 | C9: ORG-ADM | D9: 部门负责人 | E9: 现行 | F9: 行政、人力资源和培训管理 | G9: 制度建设、人事档案、招聘离职、培训考核、企业文化建设 | H9: 《安全管理台账》、《安全教育培训台账》 | I9: 招聘、解雇及行政审批权限待确认 | J9: 人事、培训和行政管理能力待确认 | K9: POS-GM
A10: POS-PROD-MGR | B10: 生产部负责人 | C10: ORG-PROD | D10: 部门负责人 | E10: 现行 | F10: 对生产部整体交付、产能、安全、质量、成本结果承担最终责任；统筹生产资源、审批计划、处置重大生产问题，对接各部门达成订单交付目标 | G10: 承接公司生产目标，审批生产计划员编制的排产及任务草案；统筹各车间人力、设备、模具资源；决策处置停线、批量不良等重大生产异常；监督生产安全、5S及设备管理；跨部门协调交期、质量冲突；审核生产汇总报表，向总经理汇报绩效。 | H10: 《生产任务单（审批版）》、《生产异常汇总报告》、《生产部月度绩效汇总》、《重大生产异常处置意见》 | I10: 生产计划审批权；生产资源调度权；生产停线/恢复生产决定权；生产绩效审核权；重大生产异常处置决策权；无具体单据编制权限 | J10: 制造业生产全盘管理；产能评估；跨部门沟通协调；现场安全与人员管理；异常风险决策能力 | K10: POS-GM
A11: POS-QA-MGR | B11: 品质部负责人 | C11: ORG-QA | D11: 部门负责人 | E11: 现行 | F11: 质量检验与质量体系管理 | G11: 来料、制程、最终检验、不合格处置、客诉处理、量具管理、文件控制、6S和持续改进 | H11: 《IQC来料检验报告》、《客诉闭环报告》、《量具校准台账》、《受控质量文件清单》 | I11: 允收/拒收、放行、隔离和客诉改善权限待确认 | J11: 质量检验、根因分析、体系和统计技术能力待确认 | K11: POS-GM
A12: POS-TECH-MGR | B12: 模具技术负责人 | C12: ORG-PROD-TECH | D12: 班组负责人 | E12: 现行 | F12: 模具维修与技术管理 | G12: 模具维修技术支持；模具维修方案评审；模具技术问题攻关；维修工艺优化；技术文档编制；对接生产和模具维修组 | H12: 《模具技术评审记录》、《维修技术方案》、《技术改善报告》 | I12: 模具维修技术方案评审、维修工艺建议权限 | J12: 模具维修、模具技术问题攻关、维修工艺和现场技术支持 | K12: POS-PROD-MGR
A13: POS-PROD-SH-SUP | B13: 冲压车间负责人 | C13: ORG-PROD-WORK | D13: 班组负责人 | E13: 现行 | F13: 承接生产部审批后的正式生产任务，统筹冲压车间人员、设备、生产、安全、5S，保障车间按质按量完成产出，及时上报各类生产异常 | G13: 执行生产部下达正式生产任务，安排班组生产作业；车间人员排班、工位调配，落实安全与5S管理；监督设备点检，发起设备/模具故障报修；汇总生产日报，隔离现场不良并上报异常；配合模具组完成上机、换模试模；开展安全巡检，闭环现场隐患。 | H13: 《冲压车间工位生产日报汇总》、《冲压车间异常反馈单》、《冲床设备点检汇总表》、《车间安全&5S巡检记录》 | I13: 车间内部人员与工位调度权；现场异常上报权；设备故障报修发起权；无生产计划审批权、无权变更生产任务 | J13: 冲压现场生产管理；冲床设备基础认知；人员排班调度；生产进度管控；安全5S管理；异常识别上报能力 | K13: POS-PROD-MGR
A14: POS-PROD-WASH-MGR | B14: 清洗车间负责人 | C14: ORG-PROD-WASH | D14: 班组负责人 | E14: 现行 | F14: 清洗车间班组管理，清洗任务统筹，人员排班 | G14: 清洗生产任务分派；人员排班；设备状态监控；班组5S安全；作业质量监督；异常协调 | H14: 《清洗作业计划》、《班组巡检记录》 | I14: 班组任务调度、现场异常协调权限 | J14: 产品清洗工艺、班组现场管理 | K14: POS-PROD-WASH
A15: POS-PROD-PLAN | B15: 生产计划员 | C15: ORG-PROD | D15: 部门成员 | E15: 现行 | F15: 承接订单信息，完成生产计划编制、物料齐套核查、进度跟踪，输出计划方案提交生产部负责人审批，跟进车间执行进度，反馈交期风险 | G15: 编制主生产排产计划；开展物料齐套核查；统计产量 | H15: 《生产排产计划表》、《物料齐套核查表》、《日产量报表》、《月产量报表》 | I15: 计划草案编制权；物料齐套核查权；生产进度跟踪权；交期风险上报权；无计划审批权，不得直接下发正式生产任务 | J15: 看得懂产品图纸工艺；生产排产编制；物料齐套分析；订单交期管控；台账报表编制；跨班组信息沟通；知晓本岗位输出方案需要上级审批 | K15: POS-PROD-MGR
A16: POS-ADM-SEC | B16: 门卫 | C16: ORG-ADM-LOG | D16: 班组成员 | E16: 现行 | F16: 厂区人员、车辆出入管控，厂区安保巡逻 | G16: 人员进出登记；外来访客登记；车辆进出管理；厂区夜间巡逻；厂区安防异常上报 | H16: 《访客出入登记本》、《厂区巡逻记录》 | I16: 出入登记核查权限 | J16: 服从排班，安保值守，基础应急识别 | K16: POS-CHAIR
... A34: POS-OPS-PUR | B34: 采购员 | C34: ORG-OPS-PUR | D34: 班组成员 | E34: 现行 | F34: 物料采购执行，供应商对接，交期跟进，采购单据处理 | G34: 物料需求接收；询比价；下达采购订单；跟进物料交期；供应商沟通；来料异常对接；采购台账登记 | H34: 《采购订单》、《询比价记录》、《采购交期跟进台账》 | I34: 采购执行下单权限，采购价格审批遵循RACI | J34: 物料识别，询比价，供应商沟通，采购跟单补齐说明 | K34: POS-QA-MGR

Sheet 04_RACI职责矩阵
A1: 04RACI职责矩阵
A2: R=执行，A=最终负责/批准，C=事前咨询，I=结果知会，—=不参与。每行只能有一个A，至少一个R；角色名先在表头改成真实岗位/部门。
A4: 事项ID* | B4: 管理域 | C4: 流程/场景 | D4: 具体事项* | E4: 关键输出物 | F4: 触发条件/频次 | G4: 董事长 | H4: 总经理 | I4: 生产部 | J4: 品质部 | K4: 营运部 | L4: 行政部 | M4: 财务部 | N4: 工程技术组 | O4: 冲压车间 | P4: 模具维修组 | Q4: 清洗车间 | R4: 制程巡检组 | S4: 成品出货检验组 | T4: 业务组 | U4: 采购组 | V4: 仓储组 | W4: 后勤组 | X4: A数量 | Y4: R数量 | Z4: 检查结果 | AA4: 确认人 | AB4: 确认日期 | AC4: 备注
A5: RACI-001 | B5: 经营管理 | C5: 公司组织架构 | D5: 确认部门、岗位和汇报关系 | E5: 1、《组织架构确认版》 | F5: 组织架构调整时 | G5: A | H5: R | I5: I | J5: I | K5: I | L5: I | M5: I | N5: I | O5: I | P5: I | Q5: I | R5: I | S5: I | T5: I | U5: — | V5: — | W5: — | X5: =COUNTIF(G5:W5,"A") | Y5: =COUNTIF(G5:W5,"R") | Z5: =IF(A5="","",IF(X5<>1,"A数量必须=1",IF(Y5<1,"至少需要1个R","OK"))) | AA5: 王勇 | AB5: 2026.10.4 | AC5: 董事长最终负责，总经理牵头执行落地
A6: RACI-002 | B6: 经营管理 | C6: 年度经营目标 | D6: 确认年度经营目标和重点事项 | E6: 1、《年度经营目标表》 | F6: 年度/重大调整 | G6: I | H6: A | I6: R | J6: R | K6: R | L6: R | M6: R | N6: R | O6: R | P6: R | Q6: R | R6: R | S6: R | T6: R | U6: R | V6: R | W6: — | X6: =COUNTIF(G6:W6,"A") | Y6: =COUNTIF(G6:W6,"R") | Z6: =IF(A6="","",IF(X6<>1,"A数量必须=1",IF(Y6<1,"至少需要1个R","OK"))) | AA6: 王晓华 | AB6: 2026.10.4 | AC6: 总经理最终负责，各部门承接并分解经营目标
A7: RACI-003 | B7: 经营管理 | C7: 重大生产异常处置 | D7: 生产停线、批量不良事件评估、处置决策 | E7: 1、《重大生产异常处置报告》 | F7: 发生重大生产停线/批量不良时 | G7: — | H7: A | I7: R | J7: C | K7: C | L7: — | M7: — | N7: C | O7: R | P7: R | Q7: R | R7: R | S7: R | T7: C | U7: C | V7: C | W7: — | X7: =COUNTIF(G7:W7,"A") | Y7: =COUNTIF(G7:W7,"R") | Z7: =IF(A7="","",IF(X7<>1,"A数量必须=1",IF(Y7<1,"至少需要1个R","OK"))) | AA7: 王晓华 | AB7: 2026.10.4 | AC7: 总经理最终决策，冲压车间、清洗车间、品质、营运、工程技术协同处置重大生产异常
A8: RACI-004 | B8: 客户/订单 | C8: 订单接收与评审 | D8: 确认客户订单、图纸、交期和生产可行性 | E8: 1、《订单评审记录》 | F8: 收到新订单时 | G8: — | H8: I | I8: R | J8: R | K8: A | L8: — | M8: I | N8: R | O8: C | P8: C | Q8: C | R8: C | S8: C | T8: R | U8: R | V8: R | W8: — | X8: =COUNTIF(G8:W8,"A") | Y8: =COUNTIF(G8:W8,"R") | Z8: =IF(A8="","",IF(X8<>1,"A数量必须=1",IF(Y8<1,"至少需要1个R","OK"))) | AA8: 王秋红 | AB8: 2026.10.4 | AC8: 营运部最终负责；生产、品质、工程技术、业务组、采购组、仓储组参与执行与咨询
A9: RACI-005 | B9: 采购/供应商 | C9: 物料采购寻源下单 | D9: 物料询比价、供应商确认、下达采购订单 | E9: 1、《采购订单》；2、《询比价记录》 | F9: 物料需求时 | G9: — | H9: I | I9: C | J9: C | K9: A | L9: — | M9: C | N9: — | O9: — | P9: — | Q9: — | R9: — | S9: — | T9: R | U9: R | V9: R | W9: — | X9: =COUNTIF(G9:W9,"A") | Y9: =COUNTIF(G9:W9,"R") | Z9: =IF(A9="","",IF(X9<>1,"A数量必须=1",IF(Y9<1,"至少需要1个R","OK"))) | AA9: 王晓华 | AB9: 2026.10.4 | AC9: 营运部最终负责，采购组岗位执行询比价及下单作业
A10: RACI-006 | B10: 交付 | C10: 成品包装与出货核对放行 | D10: 成品包装贴标、出货核对、出货检验 | E10: 1、《出货通知单》；2、《检验记录》 | F10: 出货时 | G10: — | H10: I | I10: C | J10: A | K10: R | L10: — | M10: I | N10: — | O10: — | P10: — | Q10: — | R10: R | S10: R | T10: R | U10: R | V10: R | W10: — | X10: =COUNTIF(G10:W10,"A") | Y10: =COUNTIF(G10:W10,"R") | Z10: =IF(A10="","",IF(X10<>1,"A数量必须=1",IF(Y10<1,"至少需要1个R","OK"))) | AA10: 王秋红 | AB10: 2026.10.4 | AC10: 品质部最终负责；仓储包装、成品出货检验组完成，营运部业务组协同完成出货放行
A11: RACI-007 | B11: 生产 | C11: 生产任务落实、分配 | D11: 确认生产产品、材料、模具、设备和交期 | E11: 1、《生产任务确认单》 | F11: 开工前 | G11: — | H11: — | I11: A | J11: — | K11: — | L11: — | M11: — | N11: C | O11: R | P11: R | Q11: R | R11: R | S11: R | T11: C | U11: C | V11: C | W11: — | X11: =COUNTIF(G11:W11,"A") | Y11: =COUNTIF(G11:W11,"R") | Z11: =IF(A11="","",IF(X11<>1,"A数量必须=1",IF(Y11<1,"至少需要1个R","OK"))) | AA11: 王小平 | AB11: 2026.10.4 | AC11: 生产部最终负责，冲压车间、模具维修组、清洗车间执行相关工作
A12: RACI-008 | B12: 生产 | C12: 生产计划排产和产量统计 | D12: 编制、调整生产排产计划，统计产量 | E12: 1、《生产排产计划表》；2、《日产量》；3、《月产量》 | F12: 订单评审完成和生产异常发生时 | G12: — | H12: C | I12: A | J12: I | K12: C | L12: — | M12: — | N12: C | O12: R | P12: R | Q12: R | R12: I | S12: I | T12: C | U12: C | V12: C | W12: — | X12: =COUNTIF(G12:W12,"A") | Y12: =COUNTIF(G12:W12,"R") | Z12: =IF(A12="","",IF(X12<>1,"A数量必须=1",IF(Y12<1,"至少需要1个R","OK"))) | AA12: 李天友 | AB12: 2026.10.4 | AC12: 生产部最终负责，生产计划员、车间执行，运营、采购、仓储提供订单原材料信息。
A13: RACI-009 | B13: 生产 | C13: 车间生产、安全与5S管理 | D13: 车间安排协调、安全巡检、5S推行、隐患整改闭环 | E13: 1、《安全巡检表》；2、《5S检查记录》 | F13: 每日现场巡检时 | G13: — | H13: I | I13: A | J13: C | K13: — | L13: C | M13: — | N13: — | O13: R | P13: R | Q13: R | R13: I | S13: I | T13: — | U13: — | V13: — | W13: — | X13: =COUNTIF(G13:W13,"A") | Y13: =COUNTIF(G13:W13,"R") | Z13: =IF(A13="","",IF(X13<>1,"A数量必须=1",IF(Y13<1,"至少需要1个R","OK"))) | AA13: 王小平 | AB13: 2026.10.4 | AC13: 生产部最终负责，冲压车间、清洗车间、模具维修组执行现场巡检与隐患整改
A14: RACI-010 | B14: 生产 | C14: 清洗车间生产管控 | D14: 清洗任务分派、过程管控、产品自检 | E14: 1、《清洗作业记录》；2、《设备点检表》 | F14: 下达清洗生产任务时 | G14: — | H14: — | I14: A | J14: I | K14: — | L14: — | M14: — | N14: — | O14: — | P14: — | Q14: R | R14: I | S14: I | T14: — | U14: — | V14: — | W14: — | X14: =COUNTIF(G14:W14,"A") | Y14: =COUNTIF(G14:W14,"R") | Z14: =IF(A14="","",IF(X14<>1,"A数量必须=1",IF(Y14<1,"至少需要1个R","OK"))) | AA14: 马金军 | AB14: 2026.10.4 | AC14: 生产部最终负责，清洗车间执行清洗生产管控作业
A15: RACI-011 | B15: 质量 | C15: 来料检验IQ | D15: 供应商来料检验，判定来料合格/不合格 | E15: 1、《来料检验报告》；2、《来料异常单》 | F15: 物料到货时 | G15: — | H15: — | I15: I | J15: A | K15: C | L15: — | M15: — | N15: — | O15: — | P15: — | Q15: — | R15: — | S15: R | T15: C | U15: C | V15: C | W15: — | X15: =COUNTIF(G15:W15,"A") | Y15: =COUNTIF(G15:W15,"R") | Z15: =IF(A15="","",IF(X15<>1,"A数量必须=1",IF(Y15<1,"至少需要1个R","OK"))) | AA15: 李天友 | AB15: 2026.10.4 | AC15: 品质部最终负责，成品出货检验组执行来料检验作业
A16: RACI-012 | B16: 质量 | C16: 首件、制程检验；异常放行 | D16: 确认首件、异常隔离和恢复生产权限 | E16: 1、《首件/巡检异常记录》 | F16: 首件或异常发生时 | G16: — | H16: — | I16: — | J16: A | K16: — | L16: — | M16: — | N16: C | O16: R | P16: R | Q16: R | R16: R | S16: — | T16: I | U16: I | V16: I | W16: — | X16: =COUNTIF(G16:W16,"A") | Y16: =COUNTIF(G16:W16,"R") | Z16: =IF(A16="","",IF(X16<>1,"A数量必须=1",IF(Y16<1,"至少需要1个R","OK"))) | AA16: 李天友 | AB16: 2026.10.4 | AC16: 品质部最终负责，冲压车间、制程巡检组执行现场处置
... A19: RACI-015 | B19: 其他 | C19: 付款与费用审批 | D19: 确认付款、报销和资金审批边界 | E19: 1、《付款/费用审批记录》 | F19: 发生费用或付款时 | G19: — | H19: A | I19: C | J19: C | K19: C | L19: I | M19: R | N19: C | O19: — | P19: — | Q19: — | R19: — | S19: — | T19: C | U19: C | V19: C | W19: — | X19: =COUNTIF(G19:W19,"A") | Y19: =COUNTIF(G19:W19,"R") | Z19: =IF(A19="","",IF(X19<>1,"A数量必须=1",IF(Y19<1,"至少需要1个R","OK"))) | AA19: 王勇 | AB19: 2026.10.4 | AC19: 总经理最终审批，出纳岗位执行，各业务部门提供业务咨询信息
A20: RACI-016 | B20: 其他 | C20: 月度结账出具财务报表 | D20: 账务处理、月末关账、编制月度财务报表 | E20: 1、《会计凭证》；2、《月度财务报表》 | F20: 每月月末关账时 | H20: A | I20: — | J20: — | K20: — | L20: — | M20: R | N20: — | O20: — | P20: — | Q20: — | R20: — | S20: — | T20: — | U20: — | V20: — | W20: — | X20: =COUNTIF(G20:W20,"A") | Y20: =COUNTIF(G20:W20,"R") | Z20: =IF(A20="","",IF(X20<>1,"A数量必须=1",IF(Y20<1,"至少需要1个R","OK"))) | AA20: 王勇 | AB20: 2026.10.4 | AC20: 总经理最终审批，会计岗位负责账务报表编制执行
A21: RACI-017 | B21: 其他 | C21: 仓储管理物料出入库与盘点 | D21: 物料收料、发料、成品出入库、库存盘点 | E21: 1、《出入库单据》；2、《盘点表》 | F21: 物料收发，按月盘点时 | G21: — | H21: I | I21: C | J21: I | K21: A | L21: — | M21: I | N21: — | O21: — | P21: — | Q21: — | R21: — | S21: — | T21: R | U21: R | V21: R | W21: — | X21: =COUNTIF(G21:W21,"A") | Y21: =COUNTIF(G21:W21,"R") | Z21: =IF(A21="","",IF(X21<>1,"A数量必须=1",IF(Y21<1,"至少需要1个R","OK"))) | AA21: 王珊兰 | AB21: 2026.10.4 | AC21: 营运部最终负责，仓储组执行物料出入库及盘点工作
A22: RACI-018 | B22: 模具/设备 | C22: 模具维修保养作业 | D22: 模具故障维修、周期性保养，更新模具台账 | E22: 1、《模具维修保养记录》 | F22: 模具故障/定期保养时 | G22: — | H22: — | I22: I | J22: I | K22: — | L22: — | M22: — | N22: A | O22: — | P22: R | Q22: — | R22: — | S22: — | T22: — | U22: — | V22: — | W22: — | X22: =COUNTIF(G22:W22,"A") | Y22: =COUNTIF(G22:W22,"R") | Z22: =IF(A22="","",IF(X22<>1,"A数量必须=1",IF(Y22<1,"至少需要1个R","OK"))) | AA22: 王杰 | AB22: 2026.10.4 | AC22: 工程技术组最终负责，模具维修组执行模具维修保养作业
A23: RACI-019 | B23: 模具/设备 | C23: 冲床日常点检维护 | D23: 冲开班点检、故障报修处置 | E23: 1、《冲床点检记录》；2、《设备维修单》 | F23: 每日开班、设备故障发生时 | G23: — | H23: — | I23: A | J23: I | K23: — | L23: — | M23: — | N23: C | O23: R | P23: R | Q23: R | R23: I | S23: I | T23: — | U23: — | V23: — | W23: — | X23: =COUNTIF(G23:W23,"A") | Y23: =COUNTIF(G23:W23,"R") | Z23: =IF(A23="","",IF(X23<>1,"A数量必须=1",IF(Y23<1,"至少需要1个R","OK"))) | AA23: 王小平 | AB23: 2026.10.4 | AC23: 生产部最终负责，冲压车间执行冲床点检维护工作
A24: RACI-020 | B24: 模具/设备 | C24: 清洗设备日常点检维护 | D24: 清洗设备开班点检、故障报修处置 | E24: 1、《清洗设备点检记录》；2、《设备维修单》 | F24: 每日开班、设备故障发生时 | G24: — | H24: — | I24: A | J24: I | K24: — | L24: — | M24: — | N24: C | O24: R | P24: R | Q24: R | R24: I | S24: I | T24: — | U24: — | V24: — | W24: — | X24: =COUNTIF(G24:W24,"A") | Y24: =COUNTIF(G24:W24,"R") | Z24: =IF(A24="","",IF(X24<>1,"A数量必须=1",IF(Y24<1,"至少需要1个R","OK"))) | AA24: 马金军 | AB24: 2026.10.4 | AC24: 生产部最终负责，清洗车间执行清洗设备点检维护工作
A25: RACI-021 | B25: 产品/技术 | C25: 模具维修与模具技改 | D25: 模具维修技术支持；模具维修方案评审；模具技术问题攻关；维修工艺优化；技术文档编制；对接生产和模具维修组 | E25: 1、《模具评审记录》；2、《工艺文件》 | F25: 模具维修技术疑难问题、技改发生时 | G25: — | H25: C | I25: R | J25: C | K25: C | L25: — | M25: — | N25: A | O25: R | P25: R | Q25: R | R25: — | S25: — | T25: — | U25: — | V25: — | W25: — | X25: =COUNTIF(G25:W25,"A") | Y25: =COUNTIF(G25:W25,"R") | Z25: =IF(A25="","",IF(X25<>1,"A数量必须=1",IF(Y25<1,"至少需要1个R","OK"))) | AA25: 刘东 | AB25: 2026.10.4 | AC25: 工程技术组最终负责；总经理、生产部、品质部、模具维修组参与方案评审
A26: RACI-022 | B26: 行政/人事 | C26: 员工入离职手续办理 | D26: 入职登记、合同签订、离职审批及手续办理 | E26: 1、《员工档案》；2、《入离职表单》 | F26: 人员入职、离职发生时 | G26: — | H26: A | I26: C | J26: C | K26: — | L26: R | M26: I | N26: — | O26: — | P26: — | Q26: — | R26: — | S26: — | T26: — | U26: — | V26: — | W26: — | X26: =COUNTIF(G26:W26,"A") | Y26: =COUNTIF(G26:W26,"R") | Z26: =IF(A26="","",IF(X26<>1,"A数量必须=1",IF(Y26<1,"至少需要1个R","OK"))) | AA26: 王晓华 | AB26: 2026.10.4 | AC26: 总经理最终审批，行政部人事员办理入离职实操工作
A27: RACI-023 | B27: 行政/人事 | C27: 考勤统计核算基础数据 | D27: 考勤收集、加班核对，输出月度考勤表 | E27: 1、《月度考勤汇总表》 | F27: 每月月末时 | G27: — | H27: A | I27: C | J27: C | K27: — | L27: R | M27: I | N27: — | O27: — | P27: — | Q27: — | R27: — | S27: — | T27: — | U27: — | V27: — | W27: — | X27: =COUNTIF(G27:W27,"A") | Y27: =COUNTIF(G27:W27,"R") | Z27: =IF(A27="","",IF(X27<>1,"A数量必须=1",IF(Y27<1,"至少需要1个R","OK"))) | AA27: 王晓华 | AB27: 2026.10.4 | AC27: 总经理最终审批，行政部人事员完成考勤统计核算
A28: RACI-024 | B28: 行政/人事 | C28: 厂区安保及食堂管理 | D28: 门卫值守访客登记、食堂餐食及后勤环境管理 | E28: 1、《访客登记本》；2、《食堂消毒记录》 | F28: 日常持续运行时 | G28: — | H28: — | I28: — | J28: — | K28: — | L28: A | M28: I | N28: — | O28: — | P28: — | Q28: — | R28: — | S28: — | T28: — | U28: — | V28: — | W28: R | X28: =COUNTIF(G28:W28,"A") | Y28: =COUNTIF(G28:W28,"R") | Z28: =IF(A28="","",IF(X28<>1,"A数量必须=1",IF(Y28<1,"至少需要1个R","OK"))) | AA28: 王晓华 | AB28: 2026.10.4 | AC28: 行政部负责，后勤岗位（门卫、炊事员）开展安保食堂日常作业
Z29: =IF(A29="","",IF(X29<>1,"A数量必须=1",IF(Y29<1,"至少需要1个R","OK")))
Z30: =IF(A30="","",IF(X30<>1,"A数量必须=1",IF(Y30<1,"至少需要1个R","OK")))
Z31: =IF(A31="","",IF(X31<>1,"A数量必须=1",IF(Y31<1,"至少需要1个R","OK")))
Z32: =IF(A32="","",IF(X32<>1,"A数量必须=1",IF(Y32<1,"至少需要1个R","OK")))
Z33: =IF(A33="","",IF(X33<>1,"A数量必须=1",IF(Y33<1,"至少需要1个R","OK")))
Z34: =IF(A34="","",IF(X34<>1,"A数量必须=1",IF(Y34<1,"至少需要1个R","OK")))
Z35: =IF(A35="","",IF(X35<>1,"A数量必须=1",IF(Y35<1,"至少需要1个R","OK")))
Z36: =IF(A36="","",IF(X36<>1,"A数量必须=1",IF(Y36<1,"至少需要1个R","OK")))
Z37: =IF(A37="","",IF(X37<>1,"A数量必须=1",IF(Y37<1,"至少需要1个R","OK")))
Z38: =IF(A38="","",IF(X38<>1,"A数量必须=1",IF(Y38<1,"至少需要1个R","OK")))
Z39: =IF(A39="","",IF(X39<>1,"A数量必须=1",IF(Y39<1,"至少需要1个R","OK")))
Z40: =IF(A40="","",IF(X40<>1,"A数量必须=1",IF(Y40<1,"至少需要1个R","OK")))
... Z86: =IF(A86="","",IF(X86<>1,"A数量必须=1",IF(Y86<1,"至少需要1个R","OK")))

Sheet 05_确认清单
A1: 05｜组织架构与职责待确认清单
A2: 这里不是“意见收集箱”，而是管理层必须作出明确决定的事项清单。负责人、审批权和边界没有确认，就不能把文件树和流程固化。
A4: 确认编号 | B4: 确认事项 | C4: 涉及组织/岗位 | D4: 当前状态 | E4: 建议确认人 | F4: 确认结论 | G4: 生效日期 | H4: 证据/依据 | I4: 后续动作 | J4: 责任人 | K4: 截止日期 | L4: 备注
A5: CONF-001 | B5: 补录董事长姓名、员工ID和联系方式 | C5: 公司治理 | D5: 已确认 | E5: 公司负责人 | F5: 董事长为王勇（EMP-0020）；ORG-CHAIR为公司层级组织单元，ORG-ROOT负责人保持“/”。 | G5: 46299 | H5: 原始机构图只提供岗位名称 | I5: 补录人员主数据 | J5: 待确认
A6: CONF-002 | B6: 补录总经理姓名、员工ID和直接上级关系 | C6: 公司治理 | D6: 已确认 | E6: 公司负责人 | F6: 总经理为王晓华（EMP-0019）；员工上级员工ID为“/”；与董事长并列挂在公司组织单元下，不建立员工直接汇报线。 | G6: 46299 | H6: 原始机构图只提供岗位名称 | I6: 补录人员主数据 | J6: 待确认
A7: CONF-003 | B7: 确认生产部负责人及工程技术组/冲压车间/模具维修组归属 | C7: 生产部 | D7: 已确认 | E7: 总经理 | H7: 机构图给出层级位置，未给负责人 | I7: 补录部门负责人和岗位 | J7: 待确认
A8: CONF-005 | B8: 确认营运部负责人及业务、采购组、仓储组归属 | C8: 营运部 | D8: 已确认 | E8: 总经理 | H8: 机构图给出层级位置，未给职责边界 | I8: 建立运营职责矩阵 | J8: 待确认
A9: CONF-006 | B9: 确认行政部负责人及人事、后勤归属 | C9: 行政部 | D9: 已确认 | E9: 总经理 | H9: 机构图给出层级位置，未给负责人 | I9: 建立行政职责矩阵 | J9: 待确认
A10: CONF-007 | B10: 确认财务部负责人及会计、出纳复核/审批关系 | C10: 财务部 | D10: 已确认 | E10: 董事长/总经理 | H10: 机构图只列会计、出纳单元 | I10: 建立财务授权矩阵 | J10: 待确认
A11: CONF-008 | B11: 确认董事长与总经理的直接汇报及授权关系 | C11: 公司治理 | D11: 已确认 | E11: 董事长 | H11: 机构图体现上下级位置但未说明授权边界 | I11: 填写汇报与审批关系 | J11: 待确认
A12: CONF-009 | B12: 确认质量管理体系职责由哪个现有岗位/人员承担（不是新增岗位） | C12: 品质部/总经理 | D12: 已确认 | E12: 总经理 | H12: 附件3提出管理者代表职责，但公司当前组织机构图未列此岗位；按用户确认不作为岗位名称 | I12: 在RACI中配置质量体系职责，不新增岗位 | J12: 待确认
A13: CONF-011 | B13: 确认生产部、品质部、行政部职责说明中的权限边界 | C13: 生产部/品质部/行政部 | D13: 已确认 | E13: 总经理 | H13: 附件3给出职责，但多数权限未写明批准人 | I13: 补录RACI和授权矩阵 | J13: 待确认

Sheet 06_字段字典
A1: 06｜字段字典与RACI说明
A2: 本表用于说明字段含义、填写规则和RACI代码；组织架构名称以“02_组织单元”为准，岗位名称可按实际工作自定义。
A4: 字段/代码 | B4: 含义 | C4: 填写规则 | D4: 示例 | E4: 是否必填
A5: 员工ID | B5: 人员唯一标识 | C5: 建议使用EMP-001格式；离职后不复用 | D5: EMP-001 | E5: 是
A6: 组织单元ID | B6: 部门/班组唯一标识 | C6: 建议使用ORG-生产-01格式；不使用简称代替 | D6: ORG-PROD-01 | E6: 是
A7: 岗位ID | B7: 岗位唯一标识 | C7: 建议使用POS-部门-序号格式 | D7: POS-PROD-01 | E7: 是
A8: 上级员工ID | B8: 直接汇报对象 | C8: 直接汇报对象；公司层级无员工上级时填写“/”；其他人员填写唯一直接上级员工ID。 | D8: / | E8: 是（根节点除外）
A9: A | B9: Accountable，最终负责/批准 | C9: 每项活动只能有1个A | D9: A | E9: 是
A10: R | B10: Responsible，执行责任 | C10: 每项活动至少1个R | D10: R | E10: 是
A11: C | B11: Consulted，事前咨询 | C11: 有双向沟通或专业意见输入 | D11: C | E11: 按需
A12: I | B12: Informed，结果知会 | C12: 单向通知结果 | D12: I | E12: 按需
A13: — | B13: 不参与 | C13: 不属于该事项责任范围 | D13: — | E13: 按需

Sheet 99_选项字典
A1: 组织层级 | B1: 人员状态 | C1: 任职性质 | D1: 关键岗位 | E1: 组织类型 | F1: 组织状态 | G1: 岗位状态 | H1: 管理域 | I1: RACI | J1: 确认状态 | K1: 部门名称 | L1: 组织单元 | M1: 岗位名称 | N1: 管理确认人
A2: 公司负责人 | B2: 在岗 | C2: 正式员工 | D2: 是 | E2: 公司 | F2: 现行 | G2: 现行 | H2: 组织管理 | I2: A | J2: 未确认 | K2: 生产部 | L2: 惠州市鑫犇电子有限公司 | M2: 董事长 | N2: 董事长
A3: 部门负责人 | B3: 试用 | C3: 试用员工 | D3: 否 | E3: 部门 | F3: 筹备 | G3: 筹备 | H3: 经营管理 | I3: R | J3: 讨论中 | K3: 品质部 | L3: 总经理 | M3: 总经理 | N3: 总经理
A4: 班组长 | B4: 停薪留职 | C4: 兼职/兼任 | D4: 待确认 | E4: 班组 | F4: 规划 | G4: 规划 | H4: 客户/订单 | I4: C | J4: 已确认 | K4: 营运部 | L4: 生产部 | M4: 生产部负责人 | N4: 公司负责人
A5: 专业岗位 | B5: 离职交接 | C5: 外包/临时 | E5: 职能单元 | F5: 停用 | G5: 停用 | H5: 产品/技术 | I5: I | J5: 暂缓 | K5: 行政部 | L5: 工程技术组 | M5: 品质部负责人 | N5: 生产部负责人
A6: 操作岗位 | B6: 已离职 | C6: 待确认 | E6: 岗位单元 | F6: 待确认 | G6: 待确认 | H6: 生产 | I6: — | J6: 取消 | K6: 财务部 | L6: 生产车间 | M6: 营运部负责人 | N6: 品质部负责人
A7: 辅助岗位 | B7: 待确认 | E7: 项目组 | H7: 模具/设备 | K7: 公司治理 | L7: 模具维修组 | M7: 行政部负责人 | N7: 营运部负责人
A8: 待确认 | E8: 其他 | H8: 质量 | K8: 待确认 | L8: 品质部 | M8: 财务部负责人 | N8: 行政部负责人
E9: 科室 | H9: 行政/人事 | L9: 成品出货检验组 | M9: 品质经理 | N9: 财务部负责人
H10: 采购/供应商 | L10: 成品出货检验组 | M10: 工程 | N10: 待确认
H11: 交付 | L11: 营运部 | M11: 品检
H12: 改善/审核 | L12: 业务组 | M12: 质检
H13: 财务 | L13: 采购组 | M13: 巡检工
H14: 其他 | L14: 仓储组 | M14: 冲床操作工
L15: 行政部 | M15: 产品清洗工
L16: 人事组 | M16: 包装部
L17: 后勤组 | M17: 仓库
L18: 财务部 | M18: 模具维修技术工
L19: 会计组 | M19: 模具维修工
L20: 出纳组 | M20: 模具学徒
L21: 待确认 | M21: 办公文员
M22: 食堂
M23: 保安
M24: 门卫
M25: 财务
M26: 清洗主管
M27: 待确认
