Workbook
Name Opt_RACI: '99_选项字典'!$I$2:$I$6
Name Opt_部门名称: '99_选项字典'!$K$2:$K$8
Name Opt_岗位名称: '99_选项字典'!$M$2:$M$27
Name Opt_岗位状态: '99_选项字典'!$G$2:$G$6
Name Opt_关键岗位: '99_选项字典'!$D$2:$D$4
Name Opt_管理确认人: '99_选项字典'!$N$2:$N$10
Name Opt_管理域: '99_选项字典'!$H$2:$H$14
Name Opt_确认状态: '99_选项字典'!$J$2:$J$6
Name Opt_人员状态: '99_选项字典'!$B$2:$B$7
Name Opt_任职性质: '99_选项字典'!$C$2:$C$6
Name Opt_组织层级: '99_选项字典'!$A$2:$A$8
Name Opt_组织单元: '99_选项字典'!$L$2:$L$20
Name Opt_组织类型: '99_选项字典'!$E$2:$E$8
Name Opt_组织状态: '99_选项字典'!$F$2:$F$6

Sheet 00_总览与说明
A1: 鑫犇电子有限公司｜组织架构与职责矩阵模板
A2: 先填主数据，再生成管理结论。不要直接在RACI里凭感觉填部门名称；所有人员、部门、岗位先在主数据表建立唯一编号。
A4: 模板使用顺序
A5: 步骤 | B5: 工作表 | C5: 填写要求
A6: 1 | B6: 01_员工名单 | C6: 一行一个人；员工ID和上级员工ID是组织树的骨架。
A7: 2 | B7: 02_组织单元 | C7: 一行一个部门/班组/项目组；组织单元ID必须唯一。
A8: 3 | B8: 03_岗位字典 | C8: 一行一个岗位；岗位ID用于后续职责、能力和替代人管理。
A9: 4 | B9: 04_RACI职责矩阵 | C9: 一行一项管理活动；每行只能有一个A，至少一个R。
A10: 5 | B10: 05_确认清单 | C10: 将负责人、审批权、兼岗和边界争议登记，不要靠口头记忆。
A13: 质量规则（必须遵守）
A14: • 组织树：根节点只有一个；除根节点外，每个人必须有且只有一个直接上级员工ID。
A15: • RACI：每项活动必须且只能有一个A；没有A的事项不能视为已授权；至少一个R负责执行。
A16: • 职责：A是最终对结果负责和有批准权的人，不是“参与过的人”；R是实际做事的人。
A17: • 状态：当前事实和未来规划分开；不确定信息统一写“待确认”，不得凭经验补全。
A18: • 版本：修改组织关系、岗位或职责矩阵时，填写变更日期、变更原因和确认人。
A21: 自动检查看板
A22: 指标 | B22: 数值 | C22: 解释
A23: 人员总数 | B23: =COUNTIF('01_员工名单'!A5:A102,"<>") | C23: 填写数据后自动统计
A24: 在岗人数 | B24: =COUNTIFS('01_员工名单'!A5:A102,"<>",'01_员工名单'!G5:G102,"在岗") | C24: 填写数据后自动统计
A25: 组织单元数 | B25: =COUNTIF('02_组织单元'!A5:A52,"<>") | C25: 填写数据后自动统计
A26: 岗位数 | B26: =COUNTIF('03_岗位字典'!A5:A80,"<>") | C26: 填写数据后自动统计
A27: RACI事项数 | B27: =COUNTIF('04_RACI职责矩阵'!A5:A86,"<>") | C27: 填写数据后自动统计
A28: RACI待修正事项 | B28: =COUNTIF('04_RACI职责矩阵'!V5:V86,"<>OK")-COUNTBLANK('04_RACI职责矩阵'!A5:A86) | C28: 填写数据后自动统计
A30: 本次已填入：惠州市鑫犇电子有限公司原始组织机构图中的2个公司岗位、5个部门、12个下属组织/岗位单元。组织架构骨架已确认；未完成事项仅在“05_确认清单”中跟踪。
A31: 已吸收：组织机构.xlsx、附件3岗位职责文件、职工名册20260808；员工主数据只保留姓名、工种、编号和组织归属，敏感身份与联系方式不复制。

Sheet 01_组织架构图
A1: 鑫犇电子有限公司｜现行组织架构图
A2: 最终确认版：公司为最高层级，董事长与总经理同属公司层级。结构化数据以“02_组织单元”为准。
A3: 总经理负责统筹五个一级部门；品质部由制程巡检组、成品出货检验组组成，后者承担来料、成品与出货检验。

Sheet 01_员工名单
A1: 01｜员工名单
A2: 用途：组织治理、职责分配和人员规模确认。完整人事敏感资料仅在人事主数据中管理。
A4: 员工ID | B4: 上级员工ID | C4: 姓名 | D4: 岗位名称 | E4: 兼任岗位 | F4: 员工任职阶段 | G4: 人员状态
A5: EMP-0001 | B5: EMP-0019 | C5: 王小平 | D5: 生产部负责人 | F5: 正式员工 | G5: 在岗
A6: EMP-0002 | B6: EMP-0019 | C6: 王立芳 | D6: 品质组长 | F6: 正式员工 | G6: 在岗
A7: EMP-0003 | B7: EMP-0017 | C7: 尹宗琴 | D7: 质检员 | F7: 正式员工 | G7: 在岗
A8: EMP-0004 | B8: EMP-0017 | C8: 伍伟 | D8: 质检员 | F8: 正式员工 | G8: 在岗
A9: EMP-0005 | B9: EMP-0017 | C9: 余永满 | D9: 质检员 | F9: 正式员工 | G9: 在岗
A10: EMP-0006 | B10: EMP-0017 | C10: 雷杰 | D10: 质检员 | F10: 正式员工 | G10: 在岗
A11: EMP-0007 | B11: EMP-0017 | C11: 李伟芳 | D11: 质检员 | F11: 正式员工 | G11: 在岗
A12: EMP-0008 | B12: EMP-0020 | C12: 余永珍 | D12: 炊事员 | F12: 正式员工 | G12: 在岗
A13: EMP-0009 | B13: EMP-0020 | C13: 杨达友 | D13: 门卫 | F13: 正式员工 | G13: 在岗
A14: EMP-0010 | B14: EMP-0020 | C14: 尹昌廷 | D14: 门卫 | F14: 正式员工 | G14: 在岗
A15: EMP-0011 | B15: EMP-0013 | C15: 冯文举 | D15: 仓库员 | F15: 正式员工 | G15: 在岗
A16: EMP-0012 | B16: EMP-0013 | C16: 蔡光怀 | D16: 包装工 | F16: 正式员工 | G16: 在岗
A17: EMP-0013 | B17: EMP-0017 | C17: 王珊兰 | D17: 质检员 | E17: • 仓库员 | F17: 正式员工 | G17: 在岗
A18: EMP-0014 | B18: EMP-0013 | C18: 赵荔 | D18: 包装工 | F18: 正式员工 | G18: 在岗
A19: EMP-0015 | B19: EMP-0019 | C19: 王秋红 | D19: 跟单员 | F19: 正式员工 | G19: 在岗
A20: EMP-0016 | B20: EMP-0020 | C20: 尹杰 | D20: 人事员 | E20: • 采购员 | F20: 正式员工 | G20: 在岗
A21: EMP-0017 | B21: EMP-0019 | C21: 李天友 | D21: 品质部负责人 | F21: 正式员工 | G21: 在岗
A22: EMP-0018 | B22: EMP-0019 | C22: 刘东 | D22: 模具技术负责人 | F22: 正式员工 | G22: 在岗
A23: EMP-0019 | B23: / | C23: 王晓华 | D23: 总经理 | E23: • 运营部负责人 • 行政部负责人 | F23: 正式员工 | G23: 在岗
A24: EMP-0020 | B24: / | C24: 王勇 | D24: 董事长 | E24: • 财务部负责人 | F24: 正式员工 | G24: 在岗
A25: EMP-0021 | B25: EMP-0019 | C25: 马金军 | D25: 清洗组长 | F25: 正式员工 | G25: 在岗
A26: EMP-0022 | B26: EMP-0021 | C26: 余永政 | D26: 清洗工 | F26: 正式员工 | G26: 在岗
A27: EMP-0023 | B27: EMP-0021 | C27: 雷国才 | D27: 清洗工 | F27: 正式员工 | G27: 在岗
A28: EMP-0024 | B28: EMP-0021 | C28: 王正光 | D28: 清洗工 | F28: 正式员工 | G28: 在岗
A29: EMP-0025 | B29: EMP-0021 | C29: 王文开 | D29: 清洗工 | F29: 正式员工 | G29: 在岗
A30: EMP-0026 | B30: EMP-0019 | C30: 吴闻根 | D30: 模具检修组长 | F30: 正式员工 | G30: 在岗
A31: EMP-0027 | B31: EMP-0026 | C31: 陈英坤 | D31: 模具检修工 | F31: 正式员工 | G31: 在岗
A32: EMP-0028 | B32: EMP-0026 | C32: 屠园园 | D32: 模具检修工 | F32: 正式员工 | G32: 在岗
A33: EMP-0029 | B33: EMP-0026 | C33: 邓宏军 | D33: 模具检修工 | F33: 正式员工 | G33: 在岗
A34: EMP-0030 | B34: EMP-0019 | C34: 王杰 | D34: 模具检修组长 | F34: 正式员工 | G34: 在岗
A35: EMP-0031 | B35: EMP-0026 | C35: 陈仕波 | D35: 模具检修工 | F35: 正式员工 | G35: 在岗
A36: EMP-0032 | B36: EMP-0026 | C36: 杨茗杰 | D36: 模具检修工 | F36: 正式员工 | G36: 在岗
... A49: EMP-0045 | B49: EMP-0001 | C49: 张文壕 | D49: 冲床操作工 | F49: 试用员工 | G49: 在岗

Sheet 02_组织单元
A1: 02｜组织单元主数据
A2: 公司组织架构按“公司—部门—班组”管理；董事长、总经理归入公司层级；包装不作为独立组织单元，相关人员归入仓储组。 | M2: 填写口径：主要输出物改为本组织单元每月向上一级提交的管理结果、分析报告或汇总表；原始单据作为支撑资料，不作为月度汇报物。
A4: 组织单元ID* | B4: 组织单元名称* | C4: 组织层级 | D4: 上级组织单元ID | E4: 负责人员工ID | F4: 负责人姓名（可选） | G4: 组织状态 | H4: 现有人数 | I4: 计划编制 | J4: 核心定位 | K4: 主要输出物 | L4: 备注 | M4: 月度汇报对象 | N4: 月度汇报周期 | O4: 月度汇报文件/结果
A5: ORG-ROOT | B5: 惠州市鑫犇电子有限公司 | C5: 公司 | E5: / | F5: / | G5: 现行 | J5: 公司主体 | K5: 1、《年度经营目标》；2、《重大审批记录》；3、《公司级制度文件》；4、《组织架构总文件》；5、《ISO9001质量体系文件》 | L5: 公司为组织管理概念，不配置实体负责人；本字段不填写，以“/”标记。 | M5: 董事长 | N5: 每月5日前 | O5: 1、《月度经营分析报告》；2、《重大事项审批清单》；3、《组织与授权变更记录》；4、《质量体系运行报告》
A6: ORG-OPS-WH | B6: 仓储组 | C6: 班组 | D6: ORG-OPS | E6: EMP-0013 | F6: 王珊兰 | G6: 现行 | J6: 仓储管理单元 | K6: 1、《物料出入库单据》；2、《出入库存台账（包括纸质和电子台账）》；3、《出入库存立牌》；4、《季度盘点表》 | L6: 按本次组织架构确认更新；月度汇报内容沿用原定义，后续按班组职责细化。 | M6: 运营部负责人 | N6: 每月2日前 | O6: 1、《月度库存汇总》；2、《出入库汇总》；3、《盘点差异表》；4、《呆滞物料清单》；5、《库存预警清单》
A7: ORG-OPS-PUR | B7: 采购组 | C7: 班组 | D7: ORG-OPS | E7: EMP-0016 | F7: 尹杰 | G7: 现行 | J7: 采购单元 | K7: 1、《采购订单》；2、《询比价记录》；3、《采购交期跟进台账》；4、《来料异常记录》 | L7: 按本次组织架构确认更新；月度汇报内容沿用原定义，后续按班组职责细化。 | M7: 运营部负责人 | N7: 每月2日前 | O7: 1、《月度采购完成情况》；2、《供应商交期达成率》；3、《采购价格变化》；4、《来料异常汇总》；5、《待采购物料清单》
A8: ORG-OPS-BIZ | B8: 业务组 | C8: 班组 | D8: ORG-OPS | E8: EMP-0015 | F8: 王秋红 | G8: 现行 | J8: 业务单元 | K8: 1、《订单评审记录》；2、《订单台账》；3、《客户沟通记录》；4、《出货通知单》 | L8: 按本次组织架构确认更新；月度汇报内容沿用原定义，后续按班组职责细化。 | M8: 运营部负责人 | N8: 每月2日前 | O8: 1、《月度订单台账》；2、《订单交期达成率》；3、《客户投诉与需求汇总》；4、《未交付订单清单》；5、《下月订单预测》
A9: ORG-ADM-LOG | B9: 后勤组 | C9: 班组 | D9: ORG-ADM | E9: EMP-0020 | F9: 王勇 | G9: 现行 | J9: 后勤保障单元 | K9: 1、《访客出入登记本》；2、《厂区巡逻记录》；3、《食堂消毒记录》 | L9: 按本次组织架构确认更新；月度汇报内容沿用原定义，后续按班组职责细化。 | M9: 行政部负责人 | N9: 每月2日前 | O9: 1、《月度门卫与访客情况》；2、《食堂费用/卫生情况》；3、《后勤维修事项》；4、《安全及环境异常汇总》
A10: ORG-ADM-HR | B10: 人事组 | C10: 班组 | D10: ORG-ADM | E10: EMP-0016 | F10: 尹杰 | G10: 现行 | J10: 人事管理单元 | K10: 1、《员工人事档案》；2、《入离职表单》；3、《月度考勤汇总表》；4、《招聘台账》；5、《社保办理记录》 | L10: 按本次组织架构确认更新；月度汇报内容沿用原定义，后续按班组职责细化。 | M10: 行政部负责人 | N10: 每月2日前 | O10: 1、《月度人员花名册》；2、《入离职汇总》；3、《考勤异常》；4、《招聘进度》；5、《培训与社保办理情况》
A11: ORG-QA | B11: 品质部 | C11: 部门 | D11: ORG-GM | E11: EMP-0017 | F11: 李天友 | G11: 现行 | J11: 品质管理部门 | K11: 1、《IQC来料检验报告》；2、《制程/终检检验记录》；3、《不合格品处置记录》；4、《客诉闭环报告》；5、《量具校准台账》；6、《受控质量文件》 | M11: 总经理 | N11: 每月3日前 | O11: 1、《月度质量报告》；2、《来料/制程/出货不良分析》；3、《客户投诉闭环情况》；4、《质量异常汇总》；5、《纠正预防措施跟踪》
A12: ORG-PROD | B12: 生产部 | C12: 部门 | D12: ORG-GM | E12: EMP-0001 | F12: 王小平 | G12: 现行 | J12: 生产管理部门 | K12: 1、《生产任务单》；2、《日产量报表》；3、《设备日点检汇总表》；4、《生产异常记录》 | M12: 总经理 | N12: 每月3日前 | O12: 1、《月度生产完成报告》；2、《产量与达成率分析》；3、《生产异常汇总》；4、《设备与安全5S问题汇总》；5、《下月生产计划》
A13: ORG-OPS | B13: 运营部 | C13: 部门 | D13: ORG-GM | E13: EMP-0019 | F13: 王晓华 | G13: 现行 | J13: 运营管理部门 | K13: 1、《订单评审文件》；2、《原材料采购申购单》；3、《仓储盘点汇总》；4、《出货检测报告》 | M13: 总经理 | N13: 每月3日前 | O13: 1、《月度订单执行报告》；2、《客户交期达成情况》；3、《采购交期异常》；4、《库存与出货协调情况》；5、《重点客户事项》
A14: ORG-FIN | B14: 财务部 | C14: 部门 | D14: ORG-GM | E14: EMP-0020 | F14: 王勇 | G14: 现行 | J14: 财务管理部门 | K14: 1、《会计凭证》；2、《月度财务报表》；3、《税务申报表》；4、《资金计划》；5、《付款审批记录》；6、《成本分析报告》 | M14: 董事长、总经理 | N14: 每月5日前 | O14: 1、《月度财务报表》；2、《资金收支汇总》；3、《应收应付情况》；4、《成本分析》；5、《税务事项》；6、《资金风险提示》
A15: ORG-ADM | B15: 行政部 | C15: 部门 | D15: ORG-GM | E15: EMP-0020 | F15: 王勇 | G15: 现行 | J15: 行政管理部门 | K15: 1、《文件员工档案》；2、《安全管理台账》；3、《安全教育培训台账》；4、《后勤管理记录》；5、《招聘/离职资料》 | M15: 总经理 | N15: 每月3日前 | O15: 1、《月度人事行政报告》；2、《人员异动》；3、《考勤汇总》；4、《招聘进度》；5、《培训完成情况》；6、《安全后勤事项》
A16: ORG-PROD-WORK | B16: 生产车间 | C16: 班组 | D16: ORG-PROD | E16: EMP-0001 | F16: 王小平 | G16: 现行 | J16: 生产执行单元 | K16: 1、《冲压半成品/成品》；2、《冲床设备点检记录》；3、《工位生产日报》；4、《现场不良隔离记录》 | L16: 按本次组织架构确认更新；月度汇报内容沿用原定义，后续按班组职责细化。 | M16: 生产部负责人 | N16: 每月2日前 | O16: 1、《月度产量汇总》；2、《工时/效率统计》；3、《设备点检异常汇总》；4、《现场不良与停机记录》；5、《人员出勤及加班汇总》
A17: ORG-PROD-TECH | B17: 工程技术组 | C17: 班组 | D17: ORG-PROD | E17: EMP-0018 | F17: 刘东 | G17: 现行 | J17: 技术支持单元 | K17: 1、《模具技术评审记录》；2、《产品工艺文件》；3、《技术改善报告》；4、《工艺变更建议文档》 | L17: 按本次组织架构确认更新；月度汇报内容沿用原定义，后续按班组职责细化。 | M17: 生产部负责人 | N17: 每月2日前 | O17: 1、《月度技术问题清单》；2、《模具/工艺改善报告》；3、《工艺变更建议》；4、《技术支持完成情况》；5、《未关闭问题》
A18: ORG-PROD-MOLD | B18: 模具维修组 | C18: 班组 | D18: ORG-PROD | E18: EMP-0026 | F18: 吴文根 | G18: 现行 | J18: 模具制造/维修单元 | K18: 1、《模具维修保养记录》；2、《模具台账》；3、《修模改模图纸台账》；4、《班组巡检记录》 | L18: 按本次组织架构确认更新；月度汇报内容沿用原定义，后续按班组职责细化。 | M18: 生产部负责人 | N18: 每月2日前 | O18: 1、《月度模具维修保养汇总》；2、《模具故障统计》；3、《改模任务完成情况》；4、《未完成维修事项》；5、《下月维修计划》
A19: ORG-PROD-WASH | B19: 清洗车间 | C19: 班组 | D19: ORG-PROD | E19: EMP-0021 | F19: 马金军 | G19: 现行 | J19: 产品清洗单元 | K19: 1、《清洗作业记录》；2、《清洗设备点检表》；3、《不良隔离记录》 | L19: 清洗车间已纳入现行组织架构，马金军为清洗组长。 | M19: 生产部负责人 | N19: 每月2日前 | O19: 1、《月度清洗产量统计》；2、《清洗不良汇总》；3、《设备点检异常》；4、《耗材使用汇总》；5、《下月任务需求》
A20: ORG-GM | B20: 总经理 | C20: 公司 | D20: ORG-ROOT | E20: EMP-0019 | F20: 王晓华 | G20: 现行 | J20: 公司经营管理与跨部门协调 | K20: 1、《经营管理会议纪要》；2、《月度经营分析报告》；3、《重点事项跟踪表》 | L20: 与董事长同属公司层级；负责日常经营管理和五个一级部门统筹协调。
A21: ORG-QA-FG | B21: 成品出货检验组 | C21: 班组 | D21: ORG-QA | E21: EMP-0017 | F21: 李天友 | G21: 现行 | J21: 品质管理班组 | K21: 1、《月度制程/成品检验汇总》；2、《出货质量报告》；3、《客户质量异常跟踪》 | L21: 合并承担来料检查、成品检验和出货检验职责；分别按来料、成品和出货检验要求记录与处理异常。
A22: ORG-FIN-ACC | B22: 会计组 | C22: 班组 | D22: ORG-FIN | E22: EMP-0020 | F22: 王勇 | G22: 现行 | J22: 财务班组 | K22: 1、《月度财务报表》；2、《税务申报汇总》；3、《成本分析报告》 | L22: 会计核算与税务
A23: ORG-FIN-CASH | B23: 出纳组 | C23: 班组 | D23: ORG-FIN | E23: EMP-0020 | F23: 王勇 | G23: 现行 | J23: 财务班组 | K23: 1、《月度资金收支汇总》；2、《银行对账》；3、《付款执行清单》 | L23: 资金收付与台账
A24: ORG-CHAIR | B24: 董事长 | C24: 公司 | D24: ORG-ROOT | E24: EMP-0020 | F24: 王勇 | G24: 现行 | J24: 公司治理与重大决策 | K24: 1、《战略规划文件》；2、《重大事项审批记录》 | L24: 董事长：王勇（EMP-0020）。 | M24: 公司 | N24: 每月5日前 | O24: 1、《年度经营目标》；2、《重大事项审批清单》；3、《组织与授权变更记录》
A25: ORG-QA-IPQC | B25: 制程巡检组 | C25: 班组 | D25: ORG-QA | E25: EMP-0017 | F25: 李天友 | G25: 现行 | J25: 制程质量巡检单元 | K25: 1、《制程巡检记录》；2、《制程异常反馈单》 | L25: 制程巡检、首件复核和现场不良隔离。 | M25: 品质部负责人 | N25: 每月2日前 | O25: 1、《月度制程质量汇总》；2、《制程异常汇总》；3、《未关闭质量问题》

Sheet 03_岗位字典
A1: 03｜岗位字典
A2: 岗位名称可根据实际工作需要自定义；岗位所属组织单元及岗位层级须引用“02_组织单元”中的正式架构。岗位层级格式为“公司/部门/班组＋负责人/成员”。
A4: 岗位ID* | B4: 岗位名称* | C4: 所属组织单元ID | D4: 岗位层级 | E4: 岗位状态 | F4: 岗位目的 | G4: 核心职责 | H4: 关键输出物 | I4: 关键权限 | J4: 任职要求/能力 | K4: 替代岗位ID | L4: 备注
A5: POS-CHAIR | B5: 董事长 | C5: ORG-ROOT | D5: 公司负责人 | E5: 现行 | F5: 把控公司战略方向，重大经营决策、风险管控 | G5: 公司战略规划；重大投资、人事组、财务事项审批；监督总经理经营履职；重大对外决策 | H5: 1、《战略规划文件》；2、《重大事项审批记录》 | I5: 重大投资审批权、高层人事任免权、重大财务审批权 | J5: 企业经营战略、风险管理、行业研判能力
A6: POS-GM | B6: 总经理 | C6: ORG-ROOT | D6: 公司负责人 | E6: 现行 | F6: 全面负责公司日常经营管理，对经营结果最终负责 | G6: 执行董事会战略；统筹各部门运营；经营目标拆解落地；跨部门冲突协调；经营绩效管控；重大客户与供应商管理 | H6: 1、《待确认》 | I6: 年度经营计划、经营分析报告、部门绩效目标；日常经营决策权、部门工作调度权、一般人事审批权 | J6: 制造业全盘运营管理，生产质量财务综合管理能力
A7: POS-FIN--MGR | B7: 财务部负责人 | C7: ORG-FIN | D7: 部门负责人 | E7: 现行 | F7: 统筹财务核算、资金、税务、成本管理，保障资金安全合规 | G7: 全盘账务管理；资金计划与付款审批；税务申报；成本核算；财务报表；会计出纳工作监督复核；内控风险把控 | H7: 1、《年度经营计》 | I7: 待确认 | J7: 待确认
A8: POS-OPS-MGR | B8: 运营部负责人 | C8: ORG-OPS | D8: 部门负责人 | E8: 现行 | F8: 合同订单、客户、采购和仓储运营管理 | G8: 合同/订单评审、客户沟通、业务跟单、采购组、供应商、物料入库和仓储控制 | H8: 1、《财务报表》；2、《资金计划》；3、《税务申报表》；4、《成本分析报告》 | I8: 资金付款复核审批、账务审核、财务制度拟定权 | J8: 财务全盘管理、税务、成本核算、内控风险识别
A9: POS-ADM-MGR | B9: 行政部负责人 | C9: ORG-ADM | D9: 部门负责人 | E9: 现行 | F9: 行政、人力资源和培训管理 | G9: 制度、人事档案、招聘离职、培训考核和企业文化 | H9: 1、《员工档案》；2、《培训记录》；3、《招聘/离职资料》 | I9: 招聘、解雇及行政审批权限待确认 | J9: 人事组、培训和行政管理能力待确认
A10: POS-PROD-MGR | B10: 生产部负责人 | C10: ORG-PROD | D10: 部门负责人 | E10: 现行 | F10: 生产计划与现场生产管理 | G10: 人员进出登记；外来访客登记；车辆进出管理；厂区夜间巡逻；厂区安防异常上报 | H10: 1、《访客登记本》；2、《巡逻记录》 | I10: 生产调度和停产/恢复权限待确认 | J10: 生产计划、现场管理和安全管理能力待确认
A11: POS-QA-MGR | B11: 品质部负责人 | C11: ORG-QA | D11: 部门负责人 | E11: 现行 | F11: 员工食堂食材加工、餐食制作、食堂环境卫生 | G11: 三餐制作；厨具清洁消毒；食堂区域卫生；食材保管；餐具清洗消毒 | H11: 1、《食堂就餐保障》；2、《厨具消毒记录》 | I11: 允收/拒收、放行、隔离和客诉改善权限待确认 | J11: 质量检验、根因分析、体系和统计技术能力待确认
A12: POS-ADM-SEC | B12: 门卫 | C12: ORG-ADM-LOG | D12: 班组成员 | E12: 现行 | F12: 成品包装、标识，按要求完成出货包装作业 | G12: 人员进出登记；外来访客登记；车辆进出管理；厂区夜间巡逻；厂区安防异常上报 | H12: 1、《访登记本》；2、《巡逻记录》 | I12: 出入登记核查权限 | J12: 服从排班，安保值守，基础应急识别
A13: POS-ADM-SK | B13: 炊事员 | C13: ORG-ADM-LOG | D13: 班组成员 | E13: 现行 | F13: 员工食堂食材加工、餐食制作、食堂环境卫生员工 | G13: 三餐制作；厨具清洁消毒；食堂区域卫生；食材保管；餐具清洗消毒食 | H13: 1、《堂就餐保障》；2、《厨具消毒记录食》 | I13: 堂食材使用、厨具管理权限 | J13: 食品加工，卫生操作规范
A14: POS-PROD-PK | B14: 包装工 | C14: ORG-OPS-WH | D14: 班组成员 | E14: 现行 | F14: 操作冲床设备，按工艺完成产品冲压生产 | G14: 设备开机点检；按作业指导书进行冲压作业；首件确认；生产自检；设备日常保养；工位5S；不良品隔离 | H14: 1、《包装完成成品》；2、《包装作业记录》 | I14: 包装物料领用权限 | J14: 看懂包装要求，动手包装作业
A15: POS-PROD-WH | B15: 仓库员 | C15: ORG-OPS-WH | D15: 班组成员 | E15: 现行 | F15: 物料、半成品、成品出入库，库存台账管理，仓储5S | G15: 物料收货入库；物料出库发料；成品入库出货；库位管理；盘点；物料防护；台账登记 | H15: 1、《出入库单据》；2、《库存台账》；3、《盘点表》 | I15: 物料收发、库位调整权限 | J15: 仓库账务、物料识别、盘点作业
A16: POS-PROD-STP | B16: 冲床操作工 | C16: ORG-PROD-WORK | D16: 班组成员 | E16: 现行 | F16: 操作冲床设备，按工艺完成产品冲压生产设 | G16: 维修任务分派；模具故障统筹处理；班组人员排班；模具台账管理；班组安全5S；技术经验传递 | H16: 1、《冲压半成品/成品》；2、《设备点检记录》 | I16: 班组任务调度、模具维修方案建议权限 | J16: 模具维修技能、班组现场管理
... A29: POS-OPS-PUR | B29: 采购员 | C29: ORG-OPS-PUR | D29: 班组成员 | E29: 现行 | F29: 物料采购执行，供应商对接，交期跟进，采购单据处理 | G29: 物料需求接收；询比价；下达采购订单；跟进物料交期；供应商沟通；来料异常对接；采购台账登记 | H29: 1、《采购订单》；2、《询比价记录》；3、《采购跟进台账》 | I29: 采购执行下单权限，采购价格审批遵循RACI | J29: 物料识别，询比价，供应商沟通，采购跟单补齐说明

Sheet 04_RACI职责矩阵
A1: 04｜RACI职责矩阵
A2: R=执行，A=最终负责/批准，C=事前咨询，I=结果知会，—=不参与。每行只能有一个A，至少一个R；角色名先在表头改成真实岗位/部门。
A4: 事项ID* | B4: 管理域 | C4: 流程/场景 | D4: 具体事项* | E4: 关键输出物 | F4: 触发条件/频次 | G4: 董事长 | H4: 总经理 | I4: 生产部 | J4: 品质部 | K4: 运营部 | L4: 行政部 | M4: 财务部 | N4: 工程技术组 | O4: 生产车间 | P4: 模具维修组 | Q4: 清洗车间 | R4: 成品出货检验组 | S4: 业务组/采购组/仓储组 | T4: A数量 | U4: R数量 | V4: 检查结果 | W4: 确认人 | X4: 确认日期 | Y4: 备注
A5: RACI-001 | B5: 组织管理 | C5: 公司组织架构 | D5: 确认部门、岗位和汇报关系 | E5: 1、《组织架构确认版》 | F5: 组织架构调整时 | G5: A | H5: R | I5: I | J5: I | K5: I | L5: I | M5: I | N5: I | O5: I | P5: I | Q5: I | R5: I | S5: I | T5: =COUNTIF(G5:S5,"A") | U5: =COUNTIF(G5:S5,"R") | V5: =IF(A5="","",IF(T5<>1,"A数量必须=1",IF(U5<1,"至少需要1个R","OK"))) | W5: 王勇 | X5: 2026.10.4 | Y5: 董事长承担，总经理执行入
A6: RACI-002 | B6: 经营管理 | C6: 年度经营目标 | D6: 确认年度经营目标和重点事项 | E6: 1、《年度经营目标表》 | F6: 年度/重大调整 | G6: I | H6: A | I6: R | J6: R | K6: R | L6: R | M6: R | N6: R | O6: R | P6: R | Q6: R | R6: R | S6: R | T6: =COUNTIF(G6:S6,"A") | U6: =COUNTIF(G6:S6,"R") | V6: =IF(A6="","",IF(T6<>1,"A数量必须=1",IF(U6<1,"至少需要1个R","OK"))) | W6: 王晓华 | X6: 2026.10.4 | Y6: 总经理承担，各部门承接分解目标
A7: RACI-003 | B7: 客户/订单 | C7: 订单接收与评审 | D7: 确认客户订单、图纸、交期和生产可行性 | E7: 1、《订单评审记录》 | F7: 收到新订单时 | G7: — | H7: I | I7: R | J7: R | K7: A | L7: — | M7: I | N7: R | O7: C | P7: C | Q7: C | R7: C | S7: R | T7: =COUNTIF(G7:S7,"A") | U7: =COUNTIF(G7:S7,"R") | V7: =IF(A7="","",IF(T7<>1,"A数量必须=1",IF(U7<1,"至少需要1个R","OK"))) | W7: 王秋红 | X7: 2026.10.4 | Y7: 运营部承担：生产、品质、技术、业务组、采购组、仓储组执行
A8: RACI-004 | B8: 生产 | C8: 生产任务下达 | D8: 确认生产产品、材料、模具、设备和交期 | E8: 1、《生产任务确认单》 | F8: 开工前 | G8: — | H8: — | I8: A | J8: — | K8: — | L8: — | M8: — | N8: C | O8: R | P8: R | Q8: R | R8: R | S8: C | T8: =COUNTIF(G8:S8,"A") | U8: =COUNTIF(G8:S8,"R") | V8: =IF(A8="","",IF(T8<>1,"A数量必须=1",IF(U8<1,"至少需要1个R","OK"))) | W8: 王小平 | X8: 2026.10.4 | Y8: 生产部承担，生产/模具/清洗车间执行：
A9: RACI-005 | B9: 质量 | C9: 首件与异常放行 | D9: 确认首件、异常隔离和恢复生产权限 | E9: 1、《首件/异常记录》 | F9: 首件或异常发生时 | G9: — | H9: — | I9: — | J9: A | K9: — | L9: — | M9: — | N9: C | O9: R | P9: R | Q9: R | R9: R | S9: I | T9: =COUNTIF(G9:S9,"A") | U9: =COUNTIF(G9:S9,"R") | V9: =IF(A9="","",IF(T9<>1,"A数量必须=1",IF(U9<1,"至少需要1个R","OK"))) | W9: 李天友 | X9: 2026.10.4 | Y9: 品质部承担，各生产车间、成品出货检验组执行
A10: RACI-006 | B10: 质量 | C10: 来料检验IQC | D10: 供应商来料检验，判定来料合格/不合格 | E10: 1、《来料检验报告》；2、《来料异常单》 | F10: 物料到货时 | G10: — | H10: — | I10: I | J10: A | K10: C | L10: — | M10: — | N10: — | O10: — | P10: — | Q10: — | R10: R | S10: C | T10: =COUNTIF(G10:S10,"A") | U10: =COUNTIF(G10:S10,"R") | V10: =IF(A10="","",IF(T10<>1,"A数量必须=1",IF(U10<1,"至少需要1个R","OK"))) | W10: 李天友 | X10: 2026.10.4 | Y10: 品质部承担，成品出货检验组执行
A11: RACI-007 | B11: 质量 | C11: 客户投诉闭环处理 | D11: 客户质量投诉接收、调查、制定改善措施并闭环 | E11: 1、《客诉处理报告》；2、《改善记录》 | F11: 客户反馈质量问题时 | G11: — | H11: I | I11: C | J11: A | K11: R | L11: — | M11: — | N11: C | O11: C | P11: C | Q11: C | R11: R | S11: C | T11: =COUNTIF(G11:S11,"A") | U11: =COUNTIF(G11:S11,"R") | V11: =IF(A11="","",IF(T11<>1,"A数量必须=1",IF(U11<1,"至少需要1个R","OK"))) | W11: 李天友 | X11: 2026.10.4 | Y11: 品质部承担，业务对接客户，多车间参与调查
A12: RACI-008 | B12: 财务 | C12: 付款与费用审批 | D12: 确认付款、报销和资金审批边界 | E12: 1、《付款/费用审批记录》 | F12: 发生费用或付款时 | G12: A | H12: C | I12: C | J12: C | K12: C | L12: I | M12: R | N12: C | O12: — | P12: — | Q12: — | R12: — | S12: C | T12: =COUNTIF(G12:S12,"A") | U12: =COUNTIF(G12:S12,"R") | V12: =IF(A12="","",IF(T12<>1,"A数量必须=1",IF(U12<1,"至少需要1个R","OK"))) | W12: 王勇 | X12: 2026.10.4 | Y12: 董事长承担，财务部，各部门提供业务咨询
A13: RACI-009 | B13: 财务 | C13: 月度结账出具财务报表 | D13: 账务处理、月末关账、编制月度财务报表 | E13: 1、《会计凭证》；2、《月度财务报表》 | F13: 每月月末关账时 | G13: A | H13: I | I13: — | J13: — | K13: — | L13: — | M13: R | N13: — | O13: — | P13: — | Q13: — | R13: — | S13: — | T13: =COUNTIF(G13:S13,"A") | U13: =COUNTIF(G13:S13,"R") | V13: =IF(A13="","",IF(T13<>1,"A数量必须=1",IF(U13<1,"至少需要1个R","OK"))) | W13: 王勇 | X13: 2026.10.4 | Y13: 董事长承担，会计岗位执行
A14: RACI-010 | B14: 采购组/供应链 | C14: 物料采购寻源下单 | D14: 物料采购寻源下单|物料询比价、供应商确认、下达采购订单 | E14: 1、《采购订单》；2、《询比价记录》 | F14: 物料需求时 | G14: — | H14: I | I14: C | J14: C | K14: A | L14: — | M14: C | N14: — | O14: — | P14: — | Q14: — | R14: — | S14: R | T14: =COUNTIF(G14:S14,"A") | U14: =COUNTIF(G14:S14,"R") | V14: =IF(A14="","",IF(T14<>1,"A数量必须=1",IF(U14<1,"至少需要1个R","OK"))) | W14: 王晓华 | X14: 2026.10.4 | Y14: 运营部承担，采购岗位执行
A15: RACI-011 | B15: 仓储管理 | C15: 仓储管理|物料出入库与盘点 | D15: 物料收料、发料、成品出入库、库存盘点 | E15: 1、《出入库单据》；2、《盘点表》 | F15: 物料收发，按月盘点时 | G15: — | H15: I | I15: C | J15: I | K15: A | L15: — | M15: I | N15: — | O15: — | P15: — | Q15: — | R15: — | S15: R | T15: =COUNTIF(G15:S15,"A") | U15: =COUNTIF(G15:S15,"R") | V15: =IF(A15="","",IF(T15<>1,"A数量必须=1",IF(U15<1,"至少需要1个R","OK"))) | W15: 王珊兰 | X15: 2026.10.4 | Y15: 运营部承担，仓储组执行
A16: RACI-012 | B16: 模具管理 | C16: 模具维修保养作业 | D16: 模具故障维修、周期性保养，更新模具台账 | E16: 1、《|模具维修保养记录》 | F16: 模具故障/定期保养时 | G16: — | H16: — | I16: I | J16: I | K16: — | L16: — | M16: — | N16: A | O16: — | P16: R | Q16: — | R16: — | S16: — | T16: =COUNTIF(G16:S16,"A") | U16: =COUNTIF(G16:S16,"R") | V16: =IF(A16="","",IF(T16<>1,"A数量必须=1",IF(U16<1,"至少需要1个R","OK"))) | W16: 王杰 | X16: 2026.10.4 | Y16: 模具工程技术组承担，模具维修组执行
... A21: RACI-017 | B21: 人事行政 | C21: 考勤统计核算基础数据 | D21: 考勤收集、加班核对，输出月度考勤表 | E21: 1、《月度考勤汇总表》 | F21: 每月月末时 | G21: — | H21: A | I21: C | J21: C | K21: — | L21: R | M21: I | N21: — | O21: — | P21: — | Q21: — | R21: — | S21: — | T21: =COUNTIF(G21:S21,"A") | U21: =COUNTIF(G21:S21,"R") | V21: =IF(A21="","",IF(T21<>1,"A数量必须=1",IF(U21<1,"至少需要1个R","OK"))) | W21: 王晓华 | X21: 2026.10.4 | Y21: 总经理承担，行政部人事员执行
A22: RACI-018 | B22: 后勤管理 | C22: 厂区安保及食堂管理 | D22: 门卫值守访客登记、食堂餐食及后勤环境管理 | E22: 1、《访客登记本》；2、《食堂消毒记录》 | F22: 日常持续运行时 | G22: A | H22: I | I22: — | J22: — | L22: R | M22: I | N22: — | O22: — | P22: — | Q22: — | R22: — | S22: — | T22: =COUNTIF(G22:S22,"A") | U22: =COUNTIF(G22:S22,"R") | V22: =IF(A22="","",IF(T22<>1,"A数量必须=1",IF(U22<1,"至少需要1个R","OK"))) | W22: 王勇 | X22: 2026.10.4 | Y22: 董事长承担，后勤岗位（门卫、炊事员）执行
A23: RACI-019 | B23: 出货管理 | C23: 成品包装与出货核对放行 | D23: 成品包装贴标、出货核对、出货检验 | E23: 1、《出货通知单》；2、《检验记录》 | F23: 出货时 | G23: — | H23: I | I23: C | J23: A | K23: R | L23: — | M23: I | N23: — | O23: — | P23: — | Q23: — | R23: R | S23: R | T23: =COUNTIF(G23:S23,"A") | U23: =COUNTIF(G23:S23,"R") | V23: =IF(A23="","",IF(T23<>1,"A数量必须=1",IF(U23<1,"至少需要1个R","OK"))) | W23: 王秋红 | X23: 2026.10.4 | Y23: 品质部承担，成品出货检验组、包装、仓储组，运营部业务协同
A24: RACI-020 | B24: 体系管理 | C24: 质量体系维护与内外审 | D24: 体系文件维护、内审实施、不符合项整改跟踪 | E24: 1、《受控文件清单》；2、《内审报告》 | F24: 年度内、外审时 | G24: — | H24: A | I24: C | J24: R | K24: C | L24: C | M24: — | N24: C | O24: C | P24: C | Q24: C | R24: R | S24: C | T24: =COUNTIF(G24:S24,"A") | U24: =COUNTIF(G24:S24,"R") | V24: =IF(A24="","",IF(T24<>1,"A数量必须=1",IF(U24<1,"至少需要1个R","OK"))) | W24: 王晓华 | X24: 2026.10.4 | Y24: 总经理承担，品质部执行，各部门参与参与。
A25: RACI-021 | B25: 设备工装 | C25: 冲床日常点检维护 | D25: 冲开班点检、故障报修处置 | E25: 1、《冲床点检记录》；2、《设备维修单》 | F25: 每日开班、设备故障发生时 | G25: — | H25: — | I25: A | J25: I | K25: — | L25: — | M25: — | N25: C | O25: R | P25: R | Q25: R | R25: I | S25: — | T25: =COUNTIF(G25:S25,"A") | U25: =COUNTIF(G25:S25,"R") | V25: =IF(A25="","",IF(T25<>1,"A数量必须=1",IF(U25<1,"至少需要1个R","OK"))) | W25: 王小平 | X25: 2026.10.4 | Y25: 生产部承担：生产车间执行
A26: RACI-022 | B26: 设备工装 | C26: 清洗设备常点检维护 | D26: 清洗设备开班点检、故障报修处置 | E26: 1、《清洗设备点检记录》；2、《设备维修单》 | F26: 每日开班、设备故障发生时 | G26: — | H26: — | I26: A | J26: I | K26: — | L26: — | M26: — | N26: C | O26: R | P26: R | Q26: R | R26: I | S26: — | T26: =COUNTIF(G26:S26,"A") | U26: =COUNTIF(G26:S26,"R") | V26: =IF(A26="","",IF(T26<>1,"A数量必须=1",IF(U26<1,"至少需要1个R","OK"))) | W26: 马金军 | X26: 2026.10.4 | Y26: 生产部承担：清洗车间执行
A27: RACI-023 | B27: 异常管理 | C27: |重大生产异常处置 | D27: 生产停线、批量不良事件评估、处置决策 | E27: 1、《重大生产异常处置报告》 | F27: 发生重大生产停线/批量不良时 | G27: — | H27: A | I27: R | J27: C | K27: C | L27: — | M27: — | N27: C | O27: R | P27: R | Q27: R | R27: R | S27: C | T27: =COUNTIF(G27:S27,"A") | U27: =COUNTIF(G27:S27,"R") | V27: =IF(A27="","",IF(T27<>1,"A数量必须=1",IF(U27<1,"至少需要1个R","OK"))) | W27: 王晓华 | X27: 2026.10.4 | Y27: 总经理承担，生产及各车间，品质/营运/技术协同参与执行
V28: =IF(A28="","",IF(T28<>1,"A数量必须=1",IF(U28<1,"至少需要1个R","OK")))
V29: =IF(A29="","",IF(T29<>1,"A数量必须=1",IF(U29<1,"至少需要1个R","OK")))
V30: =IF(A30="","",IF(T30<>1,"A数量必须=1",IF(U30<1,"至少需要1个R","OK")))
V31: =IF(A31="","",IF(T31<>1,"A数量必须=1",IF(U31<1,"至少需要1个R","OK")))
V32: =IF(A32="","",IF(T32<>1,"A数量必须=1",IF(U32<1,"至少需要1个R","OK")))
V33: =IF(A33="","",IF(T33<>1,"A数量必须=1",IF(U33<1,"至少需要1个R","OK")))
V34: =IF(A34="","",IF(T34<>1,"A数量必须=1",IF(U34<1,"至少需要1个R","OK")))
V35: =IF(A35="","",IF(T35<>1,"A数量必须=1",IF(U35<1,"至少需要1个R","OK")))
V36: =IF(A36="","",IF(T36<>1,"A数量必须=1",IF(U36<1,"至少需要1个R","OK")))
V37: =IF(A37="","",IF(T37<>1,"A数量必须=1",IF(U37<1,"至少需要1个R","OK")))
V38: =IF(A38="","",IF(T38<>1,"A数量必须=1",IF(U38<1,"至少需要1个R","OK")))
V39: =IF(A39="","",IF(T39<>1,"A数量必须=1",IF(U39<1,"至少需要1个R","OK")))
... V86: =IF(A86="","",IF(T86<>1,"A数量必须=1",IF(U86<1,"至少需要1个R","OK")))

Sheet 05_确认清单
A1: 05｜组织架构与职责待确认清单
A2: 这里不是“意见收集箱”，而是管理层必须作出明确决定的事项清单。负责人、审批权和边界没有确认，就不能把文件树和流程固化。
A4: 确认编号 | B4: 确认事项 | C4: 涉及组织/岗位 | D4: 当前状态 | E4: 建议确认人 | F4: 确认结论 | G4: 生效日期 | H4: 证据/依据 | I4: 后续动作 | J4: 责任人 | K4: 截止日期 | L4: 备注
A5: CONF-001 | B5: 补录董事长姓名、员工ID和联系方式 | C5: 公司治理 | D5: 已确认 | E5: 公司负责人 | H5: 原始机构图只提供岗位名称 | I5: 补录人员主数据 | J5: 待确认
A6: CONF-002 | B6: 补录总经理姓名、员工ID和直接上级关系 | C6: 公司治理 | D6: 已确认 | E6: 公司负责人 | H6: 原始机构图只提供岗位名称 | I6: 补录人员主数据 | J6: 待确认
A7: CONF-003 | B7: 确认生产部负责人及工程技术组/生产车间/模具维修组归属 | C7: 生产部 | D7: 已确认 | E7: 总经理 | H7: 机构图给出层级位置，未给负责人 | I7: 补录部门负责人和岗位 | J7: 待确认
A8: CONF-005 | B8: 确认运营部负责人及业务、采购组、仓储组归属 | C8: 运营部 | D8: 已确认 | E8: 总经理 | H8: 机构图给出层级位置，未给职责边界 | I8: 建立运营职责矩阵 | J8: 待确认
A9: CONF-006 | B9: 确认行政部负责人及人事、后勤归属 | C9: 行政部 | D9: 已确认 | E9: 总经理 | H9: 机构图给出层级位置，未给负责人 | I9: 建立行政职责矩阵 | J9: 待确认
A10: CONF-007 | B10: 确认财务部负责人及会计、出纳复核/审批关系 | C10: 财务部 | D10: 已确认 | E10: 董事长/总经理 | H10: 机构图只列会计、出纳单元 | I10: 建立财务授权矩阵 | J10: 待确认
A11: CONF-008 | B11: 确认董事长与总经理的直接汇报及授权关系 | C11: 公司治理 | D11: 已确认 | E11: 董事长 | H11: 机构图体现上下级位置但未说明授权边界 | I11: 填写汇报与审批关系 | J11: 待确认
A12: CONF-009 | B12: 确认质量管理体系职责由哪个现有岗位/人员承担（不是新增岗位） | C12: 品质部/总经理 | D12: 已确认 | E12: 总经理 | H12: 附件3提出管理者代表职责，但公司当前组织机构图未列此岗位；按用户确认不作为岗位名称 | I12: 在RACI中配置质量体系职责，不新增岗位 | J12: 待确认
A13: CONF-011 | B13: 确认生产部、品质部、行政部职责说明中的权限边界 | C13: 生产部/品质部/行政部 | D13: 未确认 | E13: 总经理 | H13: 附件3给出职责，但多数权限未写明批准人 | I13: 补录RACI和授权矩阵 | J13: 待确认

Sheet 06_字段字典
A1: 06｜字段字典与RACI说明
A2: 本表用于说明字段含义、填写规则和RACI代码；组织架构名称以“02_组织单元”为准，岗位名称可按实际工作自定义。
A4: 字段/代码 | B4: 含义 | C4: 填写规则 | D4: 示例 | E4: 是否必填
A5: 员工ID | B5: 人员唯一标识 | C5: 建议使用EMP-001格式；离职后不复用 | D5: EMP-001 | E5: 是
A6: 组织单元ID | B6: 部门/班组唯一标识 | C6: 建议使用ORG-生产-01格式；不使用简称代替 | D6: ORG-PROD-01 | E6: 是
A7: 岗位ID | B7: 岗位唯一标识 | C7: 建议使用POS-部门-序号格式 | D7: POS-PROD-01 | E7: 是
A8: 上级员工ID | B8: 直接汇报对象 | C8: 根节点留空；其他人员必须唯一对应一个上级 | D8: EMP-001 | E8: 是（根节点除外）
A9: A | B9: Accountable，最终负责/批准 | C9: 每项活动只能有1个A | D9: A | E9: 是
A10: R | B10: Responsible，执行责任 | C10: 每项活动至少1个R | D10: R | E10: 是
A11: C | B11: Consulted，事前咨询 | C11: 有双向沟通或专业意见输入 | D11: C | E11: 按需
A12: I | B12: Informed，结果知会 | C12: 单向通知结果 | D12: I | E12: 按需
A13: — | B13: 不参与 | C13: 不属于该事项责任范围 | D13: — | E13: 按需

Sheet 99_选项字典
A1: 组织层级 | B1: 人员状态 | C1: 任职性质 | D1: 关键岗位 | E1: 组织类型 | F1: 组织状态 | G1: 岗位状态 | H1: 管理域 | I1: RACI | J1: 确认状态 | K1: 部门名称 | L1: 组织单元 | M1: 岗位名称 | N1: 管理确认人
A2: 公司负责人 | B2: 在岗 | C2: 正式员工 | D2: 是 | E2: 公司 | F2: 现行 | G2: 现行 | H2: 组织管理 | I2: A | J2: 未确认 | K2: 生产部 | L2: 惠州市鑫犇电子有限公司 | M2: 董事长 | N2: 董事长
A3: 部门负责人 | B3: 试用 | C3: 试用员工 | D3: 否 | E3: 部门 | F3: 筹备 | G3: 筹备 | H3: 经营管理 | I3: R | J3: 讨论中 | K3: 品质部 | L3: 总经理 | M3: 总经理 | N3: 总经理
A4: 班组长 | B4: 停薪留职 | C4: 兼职/兼任 | D4: 待确认 | E4: 班组 | F4: 规划 | G4: 规划 | H4: 客户/订单 | I4: C | J4: 已确认 | K4: 运营部 | L4: 生产部 | M4: 生产部负责人 | N4: 公司负责人
A5: 专业岗位 | B5: 离职交接 | C5: 外包/临时 | E5: 职能单元 | F5: 停用 | G5: 停用 | H5: 产品/技术 | I5: I | J5: 暂缓 | K5: 行政部 | L5: 工程技术组 | M5: 品质部负责人 | N5: 生产部负责人
A6: 操作岗位 | B6: 已离职 | C6: 待确认 | E6: 岗位单元 | F6: 待确认 | G6: 待确认 | H6: 生产 | I6: — | J6: 取消 | K6: 财务部 | L6: 生产车间 | M6: 运营部负责人 | N6: 品质部负责人
A7: 辅助岗位 | B7: 待确认 | E7: 项目组 | H7: 模具/设备 | K7: 公司治理 | L7: 模具维修组 | M7: 行政部负责人 | N7: 运营部负责人
A8: 待确认 | E8: 其他 | H8: 质量 | K8: 待确认 | L8: 品质部 | M8: 财务部负责人 | N8: 行政部负责人
E9: 科室 | H9: 行政/人事 | L9: 成品出货检验组 | M9: 品质经理 | N9: 财务部负责人
H10: 采购/供应商 | L10: 成品出货检验组 | M10: 工程 | N10: 待确认
H11: 交付 | L11: 运营部 | M11: 品检
H12: 改善/审核 | L12: 业务组 | M12: 质检
H13: 财务 | L13: 采购组 | M13: 巡检工
H14: 其他 | L14: 仓储组 | M14: 冲床操作工
L15: 行政部 | M15: 产品清洗工
L16: 人事组 | M16: 包装部
L17: 后勤组 | M17: 仓库
L18: 财务部 | M18: 模具维修技术工
L19: 会计组 | M19: 模具维修工
L20: 出纳组 | M20: 模具学徒
L21: 待确认 | M21: 办公文员
M22: 食堂
M23: 保安
M24: 门卫
M25: 财务
M26: 清洗主管
M27: 待确认
